Workbook
Name CRF: MonitoringOptCosts!#REF!

Sheet Assumptions
A1: Flare costs are in 2019$
A2: Considered the following options:
A3: Flare with continuous natural gas (NG) pilot [Baseline]
A4: Flare with continuous NG pilot + calorimeter + flow meter
A5: Flare with continuous NG pilot + simplified VISR
A6: Flare with consistent flare gas (14-day sampling option)
A7: Flare with once every 5-year performance evaluation
A8: Used $90,000 for simplified VISR based on information collected during call with Dr. Zeng on 4/4/2022.
A9: Converted to 2019$, that is $68,493 (based on 2019 CEPCI of 607.5 and 2022 CEPCI of 816.0)

Sheet MonitoringOptCosts
A1: Control Costs for Flares with monitoring options from OOOOb Storage Tank Analysis
A2: Flare Size/Monitoring | B2: TCI | C2: AOC | D2: TAC
A3: 1 - continuous pilot, NG | B3: 79352 | C3: 22840 | D3: =B3*0.1098+C3 -> 31552.85
A4: 1 - flow+calorimeter | B4: 434667 | C4: 37052 | D4: =B4*0.1098+C4 -> 84778.437
A5: 1 - VISR | B5: 300141 | C5: 31671 | D5: =B5*0.1098+C5 -> 64626.482
A6: 2 - continuous pilot, NG | B6: 84761 | C6: 23282 | D6: =B6*0.1098+C6 -> 32588.758
A7: 2 - flow+calorimeter | B7: 440077 | C7: 37494 | D7: =B7*0.1098+C7 -> 85814.455
A8: 2 - VISR | B8: 305551 | C8: 32114 | D8: =B8*0.1098+C8 -> 65663.5
A9: 3 - continuous pilot, NG | B9: 92874 | C9: 23812 | D9: =B9*0.1098+C9 -> 34009.565
A10: 3 - flow+calorimeter | B10: 448190 | C10: 38024 | D10: =B10*0.1098+C10 -> 87235.262
A11: 3 - VISR | B11: 313664 | C11: 32643 | D11: =B11*0.1098+C11 -> 67083.307
A12: 4 - continuous pilot, NG | B12: 145328 | C12: 33526 | D12: =B12*0.1098+C12 -> 49483.014
A13: 4 - flow+calorimeter | B13: 500644 | C13: 47738 | D13: =B13*0.1098+C13 -> 102708.71
A14: 4 - VISR | B14: 366118 | C14: 42357 | D14: =B14*0.1098+C14 -> 82556.756
A15: Note: Costs are in 2019$
A16: Added Costs
A17: Flare Size/Monitoring | B17: TCI | C17: AOC | D17: TAC
A18: Flow and calorimeter | B18: =B4-B3 -> 355315 | C18: =C4-C3 -> 14212 | D18: =D4-D3 -> 53225.587
A19: VISR | B19: =B5-B3 -> 220789 | C19: =C5-C3 -> 8831 | D19: =D5-D3 -> 33073.632
A20: Added Costs Escalated to 2023$
A21: Flare Size/Monitoring | B21: TCI | C21: AOC | D21: TAC | E21: Note
A22: Flow and calorimeter | B22: =B18*B30/B26 -> 466676.28 | C22: =C18*B30/B26 -> 18666.263 | D22: =D18*B30/B26 -> 69907.318
A23: VISR | B23: =B19 -> 220789 | C23: =C19 -> 8831 | D23: =D19 -> 33073.632 | E23: Did not escalate since cost quote was from April 2022 and annual 2022 CEPCI was just slightly less than 2023.
A24: CEPCI Values
A25: Year | B25: CEPCI
A26: 2019 | B26: 607.5
A27: 2020 | B27: 596.2
A28: 2021 | B28: 708.8
A29: 2022 | B29: 816
A30: 2023 | B30: 797.9
A31: Natural Gas (NG) Costs
A32: Year | B32: NG costs ($/Mscf)
A33: 2017 | B33: 4.0683333
A34: 2018 | B34: 3.8433333
A35: 2019 | B35: 4.0558333
A36: 2020 | B36: 5.4483333
A37: 2021 | B37: 3.2625
A38: 2022 | B38: 7.7625
A39: 2023 | B39: 4.4633333
A40: 2024 | B40: 3.8841667
A41: https://www.eia.gov/dnav/ng/hist/n3035us3m.htm
A42: CRF Value
A43: CRF | B43: 0.1098
A44: Control Costs for Flares with monitoring options for MTVLO
A45: Flare Size/Monitoring | B45: TCI | C45: AOC | D45: TAC
A46: Continuous pilot, NG | B46: 211648 | C46: 37623 | D46: =B46*B43+C46 -> 60861.95
A47: Pilot plus flow and calorimeter | B47: 566964 | C47: 56342 | D47: =B47*B43+C47 -> 118594.65
A48: Pilot plus calorimeter only | B48: 414648 | C48: 50249 | D48: =B48*B43+C48 -> 95777.35
A49: Pilot plus VISR | B49: 379676 | C49: 48851 | D49: =B49*B43+C49 -> 90539.425
A50: Added Costs
A51: Flare Size/Monitoring | B51: TCI | C51: AOC | D51: TAC
A52: Flow and calorimeter | B52: =B47-B$46 -> 355316 | C52: =C47-C$46 -> 18719 | D52: =D47-D$46 -> 57732.697
A53: Calorimeter only | B53: =B48-B$46 -> 203000 | C53: =C48-C$46 -> 12626 | D53: =D48-D$46 -> 34915.4
A54: VISR | B54: =B49-B$46 -> 168028 | C54: =C49-C$46 -> 11228 | D54: =D49-D$46 -> 29677.474
A55: NG addition costs (for one-time assessment) | C55: 4507 | D55: 4507
A56: Added Costs Escalated to 2023$
A57: Flare Size/Monitoring | B57: TCI | C57: AOC | D57: TAC | E57: Note
A58: Flow and calorimeter | B58: =B52*(B30/B26) -> 466677.59 | C58: =C52*(B30/B26) -> 24585.827 | D58: =D52*(B30/B26) -> 75827.027
A59: Calorimeter only | B59: =B53*(B30/B26) -> 266623.37 | C59: =C53*(B30/B26) -> 16583.186 | D59: =D53*(B30/B26) -> 45858.432
A60: VISR | B60: =B54*(B30/B26) -> 220690.6 | C60: =C54*(B30/B26) -> 14747.031 | D60: =D54*(B30/B26) -> 38978.859 | E60: Escalated here because used descalated 2019 costs for VISR in spreadsheet input.
A61: NG addition costs (for one-time assessment) | B61: =B55*(B30/B26) -> 0 | C61: =C55*(B30/B26) -> 5919.5643 | D61: =D55*(B30/B26) -> 5919.5643
A62: Sampling Costs
A63: Item | B63: 2023 costs | C63: Basis | D63: Reference
A64: Analysis cost | B64: =ROUNDUP(200*797.9/596.2,0) -> 268 | C64: $200 for GC analysis in 2020 | D64: Fee Schedule 2020 4-17-20 new
A65: Shipping and Handling | B65: 25
A66: Labor (assuming 1 hr) | B66: =B91 -> 109.16 | C66: includes sample collection, mailing, and data review
A67: Tax | B67: =SUM(B64:B66)*0.08 -> 32.1728 | C67: assumes 8%
A68: Subtotal | B68: =SUM(B64:B67) -> 434.3328 | C68: per sample
A69: Cost of 14-day sampling option
A70: Cost | B70: Value | C70: Unit
A71: No. of samples | B71: 14
A72: Total cost of demonstration | B72: =B71*B68 -> 6080.6592
A73: Costs Annualized over 5 years | B73: =B72*$B$94 -> 1502.9244 | C73: per year
A74: Cost of Flare Performance Test
A75: Item | B75: Value | C75: Note
A76: 2-hour VE monitoring | B76: =2.5*$B$91 -> 272.9 | C76: Includes 0.5 hours for set-up
A77: Heat content anayses | B77: =8*B68 -> 3474.6624 | C77: Assumes 8 samples
A78: Flow measurement determination | B78: =B77 -> 3474.6624 | C78: Assumed comparable to heat content determinations
A79: Subtotal | B79: =SUM(B76:B78) -> 7222.2248
A80: Costs Annualized over 5 years | B80: =B79*$B$94 -> 1785.0792 | C80: per year
A81: Non-Flare performance test
A82: Item | B82: Value | C82: Note
A83: Test crew | B83: =ROUNDUP(18500*797.9/596.2,0) -> 24759 | C83: $18,500 in 2020 from gasoline distribution analysis
A84: On-site staff | B84: =4*$B$91 -> 436.64 | C84: Assumes 4 hours on-site labor.
A85: Subtotal | B85: =SUM(B83:B84) -> 25195.64
A86: Costs Annualized over 5 years | B86: =B85*$B$94 -> 6227.4733 | C86: per year
A87: Annual additional NG usage costs | B87: =B99*B39 -> 1642.953 | C87: per year
A88: Annual RATA | B88: =0.75*B83+B84 -> 19005.89 | C88: Assumes testing cost is 75% of performance test + 4 hours on-site labor.
A89: Notes for sampling costs:
A90: Item | B90: Value | C90: Note
A91: Fully Loaded Hourly Tech rate | B91: 109.16 | C91: (from memo)
A92: Interest Rate | B92: 0.075
A93: Life | B93: 5 | C93: years
A94: CRF | B94: =(B92*(1+B92)^B93)/(((1+B92)^B93)-1) -> 0.24716472
A95: Thermal combustors - operating limit ΔNG usage
A96: Item | B96: Value | C96: Unit | D96: Note
A97: Annual additional NG usage (+25 deg F) | B97: 12.27 | C97: scfm | D97: Difference in Cell D49, Design Parameters, for Oxidizer Costs, no heat recovery
A98: Low flow hours when more auxilary gas needed | B98: 500 | C98: hours | D98: Assumed needed only during low waste gas flows (Flare flow mode 3)
A99: Quantity of additional NG used | B99: =B98*60*B97/1000 -> 368.1 | C99: Mscf/year

Sheet ElectronicReporting
A1: Electronic Reporting
A2: Item | B2: Value | C2: Unit
A3: No.Facilities | B3: 190
A4: First year hrs | B4: 2 | C4: hours
A5: First year cost | B5: =B$3*B4*MonitoringOptCosts!B66 -> 41480.8
A6: Annualized | B6: =B5*B14 -> 7081.8935
A7: Subsequent time saving | B7: 2 | C7: hours
A8: Cost | B8: =-B$3*B7*MonitoringOptCosts!B66 -> -41480.8
A9: TAC | B9: =B6+B8 -> -34398.906
A10: Factors
A11: Item | B11: Value
A12: Interest Rate | B12: 0.075
A13: Life | B13: 8
A14: CRF | B14: =(B12*(1+B12)^B13)/(((1+B12)^B13)-1) -> 0.17072702

Sheet 2nd_Impacts
A1: Secondary Impacts
A2: Impact | B2: Flow/flare (Mscf/yr) | C2: Note
A3: NG usage increase for combustors | B3: =MonitoringOptCosts!B99 -> 368.1 | C3: See MonitoringOptCosts tab
A4: Natural Gas use increase for flare requirements | B4: 1088.6 | C4: Based on Cell C64 in "Design Parameters" tab for flare 101b cost sheets
A5: Secondary Impact Factors
A6: Factor | B6: Value | C6: Unit | D6: Source
A7: Natural Gas Usage | B7: 117 | C7: lb CO2/10^6 Btu | D7: Converted from Table C-1, 40 CFR part 98, subpart C
A8: Natural Gas Usage | B8: 0.068 | C8: lb NOx/10^6 Btu | D8: AP-42 Table 13.5-1
A9: Natural Gas Usage | B9: 0.31 | C9: lb CO/10^6 Btu | D9: AP-42 Table 13.5-2
A10: Natural Gas Btu | B10: 1036 | C10: Btu/scf | D10: https://www.eia.gov/energyexplained/units-and-calculators/british-thermal-units.php
A11: National Impacts
A12: Impact | B12: Flow/flare (MMscf/yr) | C12: CO2 tons/yr | D12: NOx tons/yr | E12: CO tons/yr
A13: Natural Gas use increase for theroal combustors | B13: =NationalCosts!$C$5*B3/1000 -> 36.81 | C13: =$B13*B10*B7/2000 -> 2230.9069 | D13: =$B13*B10*B8/2000 -> 1.2965954 | E13: =$B13*B10*B9/2000 -> 5.9109498
A14: Natural Gas use increase for flare requirements | B14: =NationalCosts!$C$6*B4/1000 -> 54.43 | C14: =$B14*B10*B7/2000 -> 3298.7846 | D14: =$B14*B10*B8/2000 -> 1.9172423 | E14: =$B14*B10*B9/2000 -> 8.7403694
A15: TOTAL | B15: =SUM(B13:B14) -> 91.24 | C15: =SUM(C13:C14) -> 5529.6914 | D15: =SUM(D13:D14) -> 3.2138378 | E15: =SUM(E13:E14) -> 14.651319

Sheet NationalCosts
A1: National Costs
A2: Assumed Number of Controls1 | B2: 200
A3: Assumed Breakdown of Control | B3: Fraction | C3: Number
A4: - Vapor recovery systems | B4: 0.25 | C4: =$B$2*B4 -> 50
A5: - Thermal combustor (not flare) | B5: 0.5 | C5: =$B$2*B5 -> 100
A6: - Flare | B6: 0.25 | C6: =$B$2*B6 -> 50
A7: 1 Some sources only require submerged loading but some may have multiple controls)
A8: Breakdown of Vapor Recovery Systems
A9: Monitor Type | B9: Fraction | C9: Number | D9: First Year Cost | E9: TCI | F9: AOC | G9: TAC
A10: Currently testing annually | B10: 0.2 | C10: =B10*$C$4 -> 10 | D10: 0 | E10: 0 | F10: 0 | G10: 0
A11: Subject to periodic testing | B11: 0.6 | C11: =B11*$C$4 -> 30 | D11: =MonitoringOptCosts!B85 -> 25195.64 | E11: 0 | F11: 0 | G11: =MonitoringOptCosts!B86 -> 6227.4733
A12: Subject to annual RATA | B12: =1-SUM(B10:B11) -> 0.2 | C12: =B12*$C$4 -> 10 | D12: 0 | E12: 0 | F12: =MonitoringOptCosts!B88 -> 19005.89 | G12: =F12 -> 19005.89
A13: Breakdown of Flares
A14: Monitor Type | B14: Fraction | C14: Number | D14: First Year Cost | E14: TCI | F14: AOC | G14: TAC
A15: NHV-flow monitor | B15: 0.04 | C15: =B15*$C$6 -> 2 | E15: =MonitoringOptCosts!B58 -> 466677.59 | F15: =MonitoringOptCosts!C58 -> 24585.827 | G15: =MonitoringOptCosts!D58 -> 75827.027
A16: NHV only | B16: 0.16 | C16: =B16*$C$6 -> 8 | E16: =MonitoringOptCosts!B59 -> 266623.37 | F16: =MonitoringOptCosts!C59 -> 16583.186 | G16: =MonitoringOptCosts!D59 -> 45858.432
A17: VISR | B17: 0 | C17: =B17*$C$6 -> 0 | E17: =MonitoringOptCosts!B60 -> 220690.6 | F17: =MonitoringOptCosts!C60 -> 14747.031 | G17: =MonitoringOptCosts!D60 -> 38978.859
A18: One-time assessment | B18: =1-SUM(B15:B17) -> 0.8 | C18: =B18*$C$6 -> 40 | D18: =MonitoringOptCosts!B72 -> 6080.6592 | E18: 0 | F18: =MonitoringOptCosts!C61 -> 5919.5643 | G18: =MonitoringOptCosts!B73+F18 -> 7422.4887
A19: Options
A20: Option | B20: First Year Cost | C20: Total Capital Investment, TCI ($) | D20: Annual Operating Cost, AOC ($/yr) | E20: Total Annualized Cost, TAC ($/yr) | F20: HAP Emissions Reduction (tpy) | G20: Cost-Effectiveness ($/ton HAP) | H20: VOC Emissions Reduction (tpy) | I20: Cost-Effectiveness ($/ton VOC) | J20: Comments
A21: Electronic Reporting | B21: =ElectronicReporting!B5 -> 41480.8 | D21: =ElectronicReporting!B8 -> -41480.8 | E21: =ElectronicReporting!B9 -> -34398.906
A22: Periodic Performance Testing/RATA | B22: =$C5*MonitoringOptCosts!$B85+SUMPRODUCT($C$10:$C$13,D10:D13) -> 3275433.2 | D22: =C5*MonitoringOptCosts!B87+SUMPRODUCT(C10:C13,F10:F13) -> 354354.2 | E22: =$C5*MonitoringOptCosts!$B86+D22+SUMPRODUCT(C10:C13,G10:G13) -> 1353984.6 | F22: =(C4+C5)*(B$29) -> 180 | G22: =$E22/F22 -> 7522.1368 | H22: =(C4+C5)*(B$29)*B28/B27 -> 2250 | I22: =$E22/H22 -> 601.77094 | J22: Assumes option improves average performance from 95% to 98%
A23: Enhanced Flare Monitoring | B23: =SUMPRODUCT($C15:$C18,D15:D18) -> 243226.37 | C23: =SUMPRODUCT($C15:$C18,E15:E18) -> 3066342.2 | D23: =SUMPRODUCT($C15:$C18,F15:F18) -> 418619.71 | E23: =SUMPRODUCT($C15:$C18,G15:G18) -> 815421.06 | F23: =C6*(B$30) -> 100 | G23: =$E23/F23 -> 8154.2106 | H23: =C6*(B$30)*B28/B27 -> 1250 | I23: =$E23/H23 -> 652.33685 | J23: Assumes option improves average performance from 94% to 99%
A24: Total | B24: =SUM(B21:B23) -> 3560140.4 | C24: =SUM(C21:C23) -> 3066342.2 | D24: =SUM(D21:D23) -> 731493.11 | E24: =SUM(E21:E23) -> 2135006.8 | F24: =SUM(F22:F23) -> 280 | G24: =($E22+$E23)/(F22+F23) -> 7747.8774 | H24: =SUM(H22:H23) -> 3500 | I24: =($E22+$E23)/(H22+H23) -> 619.8302
A25: Additional Factors
A26: Factor | B26: Value | C26: Unit
A27: Assumed per control inlet HAP loading | B27: 40 | C27: tons/year
A28: Assumed per control inlet VOC loading | B28: 500 | C28: tons/year
A29: HAP reductions at 3% CE improvement | B29: =B27*0.03 -> 1.2 | C29: tons/year/control
A30: HAP reductions at 5% CE improvement | B30: =B27*0.05 -> 2 | C30: tons/year/control
A31: First year costs, excluding e-reporting | B31: =C23+B23+B22 -> 6585001.7
A32: Total annualized costs, excluding e-reporting | B32: =E23+E22 -> 2169405.7
A33: Speciated HAP Emissions Reductions
A34: HAP | B34: % of total HAP | C34: Emission Reductions (tpy) for Periodic Performance Test | D34: Emission Reductions (tpy) for Enhanced Flare Monitoring | E34: Total
A35: Hexane | B35: 0.42 | C35: =B35*$F$22 -> 75.6 | D35: =B35*$F$23 -> 42 | E35: =C35+D35 -> 117.6
A36: Benzene | B36: 0.22 | C36: =B36*$F$22 -> 39.6 | D36: =B36*$F$23 -> 22 | E36: =C36+D36 -> 61.6
A37: Methanol | B37: 0.2 | C37: =B37*$F$22 -> 36 | D37: =B37*$F$23 -> 20 | E37: =C37+D37 -> 56
A38: Toluene | B38: 0.12 | C38: =B38*$F$22 -> 21.6 | D38: =B38*$F$23 -> 12 | E38: =C38+D38 -> 33.6
A39: Xylene | B39: 0.03 | C39: =B39*$F$22 -> 5.4 | D39: =B39*$F$23 -> 3 | E39: =C39+D39 -> 8.4
A40: Ethylbenzene | B40: 0.01 | C40: =B40*$F$22 -> 1.8 | D40: =B40*$F$23 -> 1 | E40: =C40+D40 -> 2.8
A41: Total HAP Reductions | B41: - | C41: =SUM(C35:C40) -> 180 | D41: =SUM(D35:D40) -> 100 | E41: =SUM(E35:E40) -> 280
A42: Secondary Impacts
A43: National Impacts | B43: Flow/flare (MMscf/yr) | C43: CO2 tons/yr | D43: NOx tons/yr | E43: CO tons/yr
A44: Natural Gas use increase for theroal combustors | B44: ='2nd_Impacts'!B13 -> 36.81 | C44: ='2nd_Impacts'!C13 -> 2230.9069 | D44: ='2nd_Impacts'!D13 -> 1.2965954 | E44: ='2nd_Impacts'!E13 -> 5.9109498
A45: Natural Gas use increase for flare requirements | B45: ='2nd_Impacts'!B14 -> 54.43 | C45: ='2nd_Impacts'!C14 -> 3298.7846 | D45: ='2nd_Impacts'!D14 -> 1.9172423 | E45: ='2nd_Impacts'!E14 -> 8.7403694
A46: Total | B46: =SUM(B44:B45) -> 91.24 | C46: =SUM(C44:C45) -> 5529.6914 | D46: =SUM(D44:D45) -> 3.2138378 | E46: =SUM(E44:E45) -> 14.651319
