Workbook
Name Average_CE: '100000MP'!$B$26
Name Average_CE: '5000000MP '!$B$15
Name Average_CE: '500000MP'!$B$16
Name VOC_Credit: '100000MP'!#REF!
Name VOC_Credit: '5000000MP '!$B$16
Name VOC_Credit: '500000MP'!$B$17

Sheet 100000MP
A1: Small Model Plant
C2: Crude Petroleum | D2: Gasoline | E2: Kerosene | F2: Distillate Fuel Oil | G2: Residual Fuel Oil | H2: Naphtha & Solvents | I2: Benzene & Toluene | J2: Alcohols | K2: Total
A3: Gallons Loaded (1000 gal/yr) | C3: 12700 | D3: 6200 | E3: 6000 | F3: 41700 | G3: 7800 | H3: 200 | I3: 13500 | J3: 11900 | K3: =SUM(C3:J3) -> 100000
A4: VOC Loading Loss (TPY) | B4: Ships | C4: =C3*'Loading Loss'!H20/2000 -> 5.860978 | D4: =D3*'Loading Loss'!B24/2000 -> 5.58 | E4: =E3*'Loading Loss'!H4/2000 -> 0.01836165 | F4: =F3*'Loading Loss'!H5/2000 -> 0.11107108 | G4: =G3*'Loading Loss'!H6/2000 -> 0.014255787 | H4: =H3*'Loading Loss'!H3/2000 -> 0.61741032 | I4: =I3*(AVERAGE('Loading Loss'!H7:H8))/2000 -> 3.1249567 | J4: =J3*(AVERAGE('Loading Loss'!H9:H10))/2000 -> 0.83638347 | K4: =SUM(C4:J4) -> 16.163417
B5: Barges | C5: =C3*'Loading Loss'!H20/2000 -> 5.860978 | D5: =D3*'Loading Loss'!C24/2000 -> 10.54 | E5: ='Loading Loss'!I4*'50000MP'!E3/2000 -> 0.0015332526 | F5: =F3*'Loading Loss'!I5/2000 -> 0.27767759 | G5: =G3*'Loading Loss'!I6/2000 -> 0.035639487 | H5: =H3*'Loading Loss'!I3/2000 -> 1.5435258 | I5: =I3*(AVERAGE('Loading Loss'!I7:I8))/2000 -> 7.8123917 | J5: =J3*(AVERAGE('Loading Loss'!I9:I10))/2000 -> 2.0909587 | K5: =SUM(C5:J5) -> 28.162705
B6: Model Plant | C6: =AVERAGE(C4:C5) -> 5.860978 | D6: =AVERAGE(D4:D5) -> 8.06 | E6: =AVERAGE(E4:E5) -> 0.0099474513 | F6: =AVERAGE(F4:F5) -> 0.19437433 | G6: =AVERAGE(G4:G5) -> 0.024947637 | H6: =AVERAGE(H4:H5) -> 1.0804681 | I6: =AVERAGE(I4:I5) -> 5.4686742 | J6: =AVERAGE(J4:J5) -> 1.4636711 | K6: =SUM(C6:J6) -> 22.163061
A7: Percent of Total Loading Loss | C7: =C6/$K$6 -> 0.26444804 | D7: =D6/$K$6 -> 0.36366818 | E7: =E6/$K$6 -> 0.00044883021 | F7: =F6/$K$6 -> 0.0087701936 | G7: =G6/$K$6 -> 0.0011256404 | H7: =H6/$K$6 -> 0.04875085 | I7: =I6/$K$6 -> 0.24674725 | J7: =J6/$K$6 -> 0.066041017 | K7: =SUM(C7:J7) -> 1
A9: Small Model Plant Emissions
B10: Benzene (TPY) | C10: Biphenyl (TPY) | D10: Chlorine (TPY) | E10: Cumene (TPY) | F10: Ethylbenzene (TPY) | G10: Ethylene Glycol (TPY) | H10: Hexane (TPY) | I10: Methanol (TPY) | J10: Napthalene (TPY) | K10: Phenol (TPY) | L10: Toluene (TPY) | M10: 2,2,4-Trimethyl-pentane (isooctane) (TPY) | N10: Styrene (TPY) | O10: Xylene (TPY) | P10: Total HAP (TPY)
A11: Ships | B11: =(C4*'Fuel Composition'!$J$32/100)+(D4*'Fuel Composition'!$J$6/100)+(E4*'Fuel Composition'!$J$87/100)+(F4*'Fuel Composition'!$J$110/100)+(G4*'Fuel Composition'!$J$135/100)+(H4*'Fuel Composition'!$J$64/100)+(I4*('Loading Loss'!H9/('Loading Loss'!H9+'Loading Loss'!H10))) -> 3.1911438 | C11: =(C4*'Fuel Composition'!$J$33/100)+(E4*'Fuel Composition'!$J$88/100)+(F4*'Fuel Composition'!$J$111/100) -> 6.0445945e-06 | D11: =G4*'Fuel Composition'!$J$137/100 -> 0.0024477186 | E11: =D4*'Fuel Composition'!$J$12/100 -> 0.00023436 | F11: =(D4*'Fuel Composition'!$J$10/100)+(C4*'Fuel Composition'!$J$35/100)+(E4*'Fuel Composition'!$J$89/100)+(F4*'Fuel Composition'!$J$112/100)+(G4*'Fuel Composition'!$J$136/100)+(H4*'Fuel Composition'!$J$74/100) -> 0.0057092378 | G11: =J4*('Loading Loss'!H10/('Loading Loss'!H10+'Loading Loss'!H9)) -> 0.0008899415 | H11: =(D4*'Fuel Composition'!$J$7/100)+(C4*'Fuel Composition'!$J$36/100)+(E4*'Fuel Composition'!$J$90/100)+(F4*'Fuel Composition'!$J$113/100)+(H4*'Fuel Composition'!$J$66/100) -> 0.26859248 | I11: =J4*('Loading Loss'!H9/('Loading Loss'!H9+'Loading Loss'!H10)) -> 0.83549353 | J11: =(D4*'Fuel Composition'!$J$13/100)+(C4*'Fuel Composition'!$J$37/100)+(E4*'Fuel Composition'!$J$91/100)+(F4*'Fuel Composition'!$J$114/100)+(G4*'Fuel Composition'!$J$138/100) -> 7.1631845e-05 | K11: =(C4*'Fuel Composition'!$J$39/100)+(E4*'Fuel Composition'!$J$92/100)+(F4*'Fuel Composition'!$J$115/100) -> 7.1462935e-05 | L11: =(D4*'Fuel Composition'!$J$8/100)+(C4*'Fuel Composition'!$J$40/100)+(E4*'Fuel Composition'!$J$93/100)+(F4*'Fuel Composition'!$J$117/100)+(G4*'Fuel Composition'!$J$139/100)+(H4*'Fuel Composition'!$J$68/100)+(I4*('Loading Loss'!H8/('Loading Loss'!H8+'Loading Loss'!H7))) -> 0.88131247 | M11: =D4*'Fuel Composition'!$J$11/100 -> 0.015624 | N11: =F4*'Fuel Composition'!$J$116/100 -> 1.1107108e-05 | O11: =(C4*'Fuel Composition'!$J$42/100)+(D4*'Fuel Composition'!$J$9/100)+(E4*'Fuel Composition'!$J$94/100)+(F4*'Fuel Composition'!$J$118/100)+(G4*'Fuel Composition'!$J$140/100)+(H4*'Fuel Composition'!$J$69/100) -> 0.023483895 | P11: =SUM(B11:O11) -> 5.2250917
A12: Barges | B12: =(C5*'Fuel Composition'!$J$32/100)+(D5*'Fuel Composition'!$J$6/100)+(E5*'Fuel Composition'!$J$87/100)+(F5*'Fuel Composition'!$J$110/100)+(G5*'Fuel Composition'!$J$135/100)+(H5*'Fuel Composition'!$J$64/100)+(I5*('Loading Loss'!H10/('Loading Loss'!H10+'Loading Loss'!H11))) -> 7.9298271 | C12: =(C5*'Fuel Composition'!$J$33/100)+(E5*'Fuel Composition'!$J$88/100)+(F5*'Fuel Composition'!$J$111/100) -> 5.8763106e-06 | D12: =G5*'Fuel Composition'!$J$137/100 -> 0.0061192999 | E12: =D5*'Fuel Composition'!$J$12/100 -> 0.00044268 | F12: =(D5*'Fuel Composition'!$J$10/100)+(C5*'Fuel Composition'!$J$35/100)+(E5*'Fuel Composition'!$J$89/100)+(F5*'Fuel Composition'!$J$112/100)+(G5*'Fuel Composition'!$J$136/100)+(H5*'Fuel Composition'!$J$74/100) -> 0.009972503 | G12: =J5*('Loading Loss'!I10/('Loading Loss'!I10+'Loading Loss'!I9)) -> 0.0022248835 | H12: =(D5*'Fuel Composition'!$J$7/100)+(C5*'Fuel Composition'!$J$36/100)+(E5*'Fuel Composition'!$J$90/100)+(F5*'Fuel Composition'!$J$113/100)+(H5*'Fuel Composition'!$J$66/100) -> 0.38914216 | I12: =J5*('Loading Loss'!I9/('Loading Loss'!I10+'Loading Loss'!I9)) -> 2.0887338 | J12: =(D5*'Fuel Composition'!$J$13/100)+(C5*'Fuel Composition'!$J$37/100)+(E5*'Fuel Composition'!$J$91/100)+(F5*'Fuel Composition'!$J$114/100)+(G5*'Fuel Composition'!$J$138/100) -> 0.0001046783 | K12: =(C5*'Fuel Composition'!$J$39/100)+(E5*'Fuel Composition'!$J$92/100)+(F5*'Fuel Composition'!$J$115/100) -> 5.9683057e-05 | L12: =(D5*'Fuel Composition'!$J$8/100)+(C5*'Fuel Composition'!$J$40/100)+(E5*'Fuel Composition'!$J$93/100)+(F5*'Fuel Composition'!$J$117/100)+(G5*'Fuel Composition'!$J$139/100)+(H5*'Fuel Composition'!$J$68/100)+(I5*('Loading Loss'!I8/('Loading Loss'!I8+'Loading Loss'!I7))) -> 2.1506209 | M12: =D5*'Fuel Composition'!$J$11/100 -> 0.029512 | N12: =F5*'Fuel Composition'!$J$116/100 -> 2.7767759e-05 | O12: =(C5*'Fuel Composition'!$J$42/100)+(D5*'Fuel Composition'!$J$9/100)+(E5*'Fuel Composition'!$J$94/100)+(F5*'Fuel Composition'!$J$118/100)+(G5*'Fuel Composition'!$J$140/100)+('100000MP'!H5*'Fuel Composition'!$J$69/100) -> 0.039875887 | P12: =SUM(B12:O12) -> 12.646669
A13: Model Plant | B13: =AVERAGE(B11:B12) -> 5.5604854 | C13: =AVERAGE(C11:C12) -> 5.9604526e-06 | D13: =AVERAGE(D11:D12) -> 0.0042835093 | E13: =AVERAGE(E11:E12) -> 0.00033852 | F13: =AVERAGE(F11:F12) -> 0.0078408704 | G13: =AVERAGE(G11:G12) -> 0.0015574125 | H13: =AVERAGE(H11:H12) -> 0.32886732 | I13: =AVERAGE(I11:I12) -> 1.4621137 | ... O13: =AVERAGE(O11:O12) -> 0.031679891 | P13: =SUM(B13:O13) -> 8.9358804
A15: Average CE | B15: 0.97
A16: VOC Credit ($/ton) | B16: 672
A18: Hours Loading | B18: Hours Loading >1.5 psia
A19: =K3*1000/42/5000 -> 476.19048 | B19: =SUM(C3,D3,H3,(0.5*I3),(0.5*J3))*1000/42/5000 -> 151.42857
A20: Total Hours Operating (1.1 factor of safety + 100 startup hours)
A21: =A19*1.1+100 -> 623.80952 | B21: =B19*1.1+100 -> 266.57143
A23: lb VOC emitted /hr | C23: VOC Reduced (TPY)
A24: (based on gasoline)
A25: =D6*2000/(D3*1000/42/5000) -> 546 | C25: =B15*SUM(C6,D6,H6,(0.74*I6),J6) -> 19.896578
B27: Carbon Adsorber | M27: Thermal Oxidizer
B28: Costs (2023 dollars) | H28: HAP Emission Reductions (tpy) | I28: HAP Cost Effectiveness ($/ton) | J28: Incremental HAP Cost Effectiveness ($/ton) | M28: Costs (2023 dollars) | Q28: HAP Emission Reductions (tpy) | R28: HAP Cost Effectiveness ($/ton) | S28: Incremental HAP Cost Effectiveness ($/ton)
B29: Capital Costs | C29: Annual Operating Costs | D29: Annual Capital Recovery | E29: Total Annual Costs | F29: Solvent Recovery Credit | G29: Total Annual Costs with Credits | M29: Capital Costs | N29: Annual Operating Costs | O29: Annual Capital Recovery | P29: Total Annual Costs
A30: Typical MTVLO Facility | L30: Typical MTVLO Facility
A31: 275 hrs (1.5 psia) | B31: 3686375 | C31: 267215 | D31: =E43*(B31-((1.08*E45*E46)+(E47*E46/E48))) -> 373972.32 | E31: =C31+D31 -> 641187.32 | F31: =B16*B15*SUM(C6,D6,H6,(0.74*I6),J6) -> 13370.5 | G31: =C31+D31-F31 -> 627816.82 | H31: =($P$13*B15*SUM(C7,D7,H7,(0.74*I7),J7)) -> 8.0220617 | I31: =G31/H31 -> 78261.28 | L31: 275 hrs (1.5 psia) | M31: 447809 | N31: 75093 | O31: =M31*O43 -> 50731.044 | P31: =N31+O31 -> 125824.04 | Q31: =H31 -> 8.0220617 | R31: =(N31+O31)/Q31 -> 15684.751
A32: 650 hrs (no exemption) | B32: 3686375 | C32: 295097 | D32: =E43*(B32-((1.08*E45*E46)+(E47*E46/E48))) -> 373972.32 | E32: =C32+D32 -> 669069.32 | F32: =K6*B16*B15 -> 14446.77 | G32: =C32+D32-F32 -> 654622.55 | H32: =$P$13*B15 -> 8.667804 | I32: =G32/H32 -> 75523.46 | J32: =(G32-G31)/(H32-H31) -> 41511.5 | L32: 650 hrs (no exemption) | M32: 447809 | N32: 153068 | O32: =M32*O43 -> 50731.044 | P32: =N32+O32 -> 203799.04 | Q32: =H32 -> 8.667804 | R32: =(N32+O32)/Q32 -> 23512.189 | S32: =(N32+O32-N31-O31)/(Q32-Q31) -> 120752.51
A35: Assumptions:
A36: 1. Loading Rate = 5000 bbl/hr
A37: 2. Ships and Barges are loaded equally
A38: 3. Up to 1 vessel can be loaded at once
D42: = CRFAdsorber × (TCI - [(1.08 x CC x Mc) + (LR x Mc/CRR)] = | N42: =CRF x TCI
D43: CRF = | E43: =(E49*(1+E49)^15)/(((1+E49)^15)-1) -> 0.11328724 | F43: Capital Recovery Factor for adsorber vessels and auxiliary equipment | N43: CRF = | O43: =(O45*(1+O45)^15)/(((1+O45)^15)-1) -> 0.11328724
D44: TCI = | E44: =B32 -> 3686375 | F44: Total Capital Investment | N44: TCI = | O44: =M31 -> 447809
D45: CC = | E45: 5.56 | F45: Carbon Cost | N45: Interest Rate | O45: 0.075
D46: Mc = | E46: 62932 | F46: Carbon Consumption
D47: LR = | E47: 44.46 | F47: Labor Rate
D48: CRR = | E48: 379 | F48: (lb/hr) Carbon Replacement Rate
D49: Interest Rate | E49: 0.075

Sheet 500000MP
A1: Medium Model Plant
C2: Crude Petroleum | D2: Gasoline | E2: Kerosene | F2: Distillate Fuel Oil | G2: Residual Fuel Oil | H2: Naphtha & Solvents | I2: Benzene & Toluene | J2: Alcohols | K2: Total
A3: Gallons Loaded (1000 gal/yr) | C3: 78300 | D3: 87000 | E3: 27400 | F3: 144400 | G3: 62400 | H3: 20900 | I3: 4100 | J3: 75500 | K3: =SUM(C3:J3) -> 500000
A4: VOC Loading Loss (TPY) | B4: Ships | C4: =C3*'Loading Loss'!H20/2000 -> 36.135006 | D4: =D3*'Loading Loss'!B24/2000 -> 78.3 | E4: =E3*'Loading Loss'!H4/2000 -> 0.083851535 | F4: =F3*'Loading Loss'!H5/2000 -> 0.38462023 | G4: =G3*'Loading Loss'!H6/2000 -> 0.1140463 | H4: =H3*'Loading Loss'!H3/2000 -> 64.519378 | I4: =I3*(AVERAGE('Loading Loss'!H7:H8))/2000 -> 0.94906092 | J4: =J3*(AVERAGE('Loading Loss'!H9:H10))/2000 -> 5.3064665 | K4: =SUM(C4:J4) -> 185.79243
B5: Barges | C5: =C3*'Loading Loss'!H20/2000 -> 36.135006 | D5: =D3*'Loading Loss'!C24/2000 -> 147.9 | E5: ='Loading Loss'!I4*'50000MP'!E3/2000 -> 0.0015332526 | F5: =F3*'Loading Loss'!I5/2000 -> 0.96155021 | G5: =G3*'Loading Loss'!I6/2000 -> 0.2851159 | H5: =H3*'Loading Loss'!I3/2000 -> 161.29845 | I5: =I3*(AVERAGE('Loading Loss'!I7:I8))/2000 -> 2.3726523 | J5: =J3*(AVERAGE('Loading Loss'!I9:I10))/2000 -> 13.266166 | K5: =SUM(C5:J5) -> 362.22047
B6: Model Plant | C6: =AVERAGE(C4:C5) -> 36.135006 | D6: =AVERAGE(D4:D5) -> 113.1 | E6: =AVERAGE(E4:E5) -> 0.042692394 | F6: =AVERAGE(F4:F5) -> 0.67308522 | G6: =AVERAGE(G4:G5) -> 0.1995811 | H6: =AVERAGE(H4:H5) -> 112.90891 | I6: =AVERAGE(I4:I5) -> 1.6608566 | J6: =AVERAGE(J4:J5) -> 9.2863164 | K6: =SUM(C6:J6) -> 274.00645
A7: Percent of Total Loading Loss | C7: =C6/$K$6 -> 0.13187648 | D7: =D6/$K$6 -> 0.41276401 | E7: =E6/$K$6 -> 0.00015580799 | F7: =F6/$K$6 -> 0.0024564576 | G7: =G6/$K$6 -> 0.00072838101 | H7: =H6/$K$6 -> 0.41206662 | I7: =I6/$K$6 -> 0.0060613778 | J7: =J6/$K$6 -> 0.033890868 | K7: =SUM(C7:J7) -> 1
A9: Medium Model Plant Emissions
B10: Benzene (TPY) | C10: Biphenyl (TPY) | D10: Chlorine (TPY) | E10: Cumene (TPY) | F10: Ethylbenzene (TPY) | G10: Ethylene Glycol (TPY) | H10: Hexane (TPY) | I10: Methanol (TPY) | J10: Napthalene (TPY) | K10: Phenol (TPY) | L10: Toluene (TPY) | M10: 2,2,4-Trimethyl-pentane (isooctane) (TPY) | N10: Styrene (TPY) | O10: Xylene (TPY) | P10: Total HAP (TPY)
A11: Ships | B11: =(C4*'Fuel Composition'!$J$32/100)+(D4*'Fuel Composition'!$J$6/100)+(E4*'Fuel Composition'!$J$87/100)+(F4*'Fuel Composition'!$J$110/100)+(G4*'Fuel Composition'!$J$135/100)+(H4*'Fuel Composition'!$J$64/100)+(I4*('Loading Loss'!H9/('Loading Loss'!H9+'Loading Loss'!H10))) -> 2.268081 | C11: =(C4*'Fuel Composition'!$J$33/100)+(E4*'Fuel Composition'!$J$88/100)+(F4*'Fuel Composition'!$J$111/100) -> 3.6973522e-05 | D11: =G4*'Fuel Composition'!$J$137/100 -> 0.019581749 | E11: =D4*'Fuel Composition'!$J$12/100 -> 0.0032886 | F11: =(D4*'Fuel Composition'!$J$10/100)+(C4*'Fuel Composition'!$J$35/100)+(E4*'Fuel Composition'!$J$89/100)+(F4*'Fuel Composition'!$J$112/100)+(G4*'Fuel Composition'!$J$136/100)+(H4*'Fuel Composition'!$J$74/100) -> 0.12043638 | G11: =J4*('Loading Loss'!H10/('Loading Loss'!H10+'Loading Loss'!H9)) -> 0.0056462675 | H11: =(D4*'Fuel Composition'!$J$7/100)+(C4*'Fuel Composition'!$J$36/100)+(E4*'Fuel Composition'!$J$90/100)+(F4*'Fuel Composition'!$J$113/100)+(H4*'Fuel Composition'!$J$66/100) -> 6.0969981 | I11: =J4*('Loading Loss'!H9/('Loading Loss'!H9+'Loading Loss'!H10)) -> 5.3008203 | J11: =(D4*'Fuel Composition'!$J$13/100)+(C4*'Fuel Composition'!$J$37/100)+(E4*'Fuel Composition'!$J$91/100)+(F4*'Fuel Composition'!$J$114/100)+(G4*'Fuel Composition'!$J$138/100) -> 0.00061642782 | K11: =(C4*'Fuel Composition'!$J$39/100)+(E4*'Fuel Composition'!$J$92/100)+(F4*'Fuel Composition'!$J$115/100) -> 0.00042004614 | L11: =(D4*'Fuel Composition'!$J$8/100)+(C4*'Fuel Composition'!$J$40/100)+(E4*'Fuel Composition'!$J$93/100)+(F4*'Fuel Composition'!$J$117/100)+(G4*'Fuel Composition'!$J$139/100)+(H4*'Fuel Composition'!$J$68/100)+(I4*('Loading Loss'!H8/('Loading Loss'!H8+'Loading Loss'!H7))) -> 1.4073672 | M11: =D4*'Fuel Composition'!$J$11/100 -> 0.21924 | N11: =F4*'Fuel Composition'!$J$116/100 -> 3.8462023e-05 | O11: =(C4*'Fuel Composition'!$J$42/100)+(D4*'Fuel Composition'!$J$9/100)+(E4*'Fuel Composition'!$J$94/100)+(F4*'Fuel Composition'!$J$118/100)+(G4*'Fuel Composition'!$J$140/100)+(H4*'Fuel Composition'!$J$69/100) -> 0.35343692 | P11: =SUM(B11:O11) -> 15.796008
A12: Barges | B12: =(C5*'Fuel Composition'!$J$32/100)+(D5*'Fuel Composition'!$J$6/100)+(E5*'Fuel Composition'!$J$87/100)+(F5*'Fuel Composition'!$J$110/100)+(G5*'Fuel Composition'!$J$135/100)+(H5*'Fuel Composition'!$J$64/100)+(I5*('Loading Loss'!H10/('Loading Loss'!H10+'Loading Loss'!H11))) -> 5.110809 | C12: =(C5*'Fuel Composition'!$J$33/100)+(E5*'Fuel Composition'!$J$88/100)+(F5*'Fuel Composition'!$J$111/100) -> 3.6150339e-05 | D12: =G5*'Fuel Composition'!$J$137/100 -> 0.048954399 | E12: =D5*'Fuel Composition'!$J$12/100 -> 0.0062118 | F12: =(D5*'Fuel Composition'!$J$10/100)+(C5*'Fuel Composition'!$J$35/100)+(E5*'Fuel Composition'!$J$89/100)+(F5*'Fuel Composition'!$J$112/100)+(G5*'Fuel Composition'!$J$136/100)+(H5*'Fuel Composition'!$J$74/100) -> 0.25602712 | G12: =J5*('Loading Loss'!I10/('Loading Loss'!I10+'Loading Loss'!I9)) -> 0.014115858 | H12: =(D5*'Fuel Composition'!$J$7/100)+(C5*'Fuel Composition'!$J$36/100)+(E5*'Fuel Composition'!$J$90/100)+(F5*'Fuel Composition'!$J$113/100)+(H5*'Fuel Composition'!$J$66/100) -> 13.287323 | I12: =J5*('Loading Loss'!I9/('Loading Loss'!I10+'Loading Loss'!I9)) -> 13.25205 | J12: =(D5*'Fuel Composition'!$J$13/100)+(C5*'Fuel Composition'!$J$37/100)+(E5*'Fuel Composition'!$J$91/100)+(F5*'Fuel Composition'!$J$114/100)+(G5*'Fuel Composition'!$J$138/100) -> 0.00098096167 | K12: =(C5*'Fuel Composition'!$J$39/100)+(E5*'Fuel Composition'!$J$92/100)+(F5*'Fuel Composition'!$J$115/100) -> 0.00036242334 | L12: =(D5*'Fuel Composition'!$J$8/100)+(C5*'Fuel Composition'!$J$40/100)+(E5*'Fuel Composition'!$J$93/100)+(F5*'Fuel Composition'!$J$117/100)+(G5*'Fuel Composition'!$J$139/100)+(H5*'Fuel Composition'!$J$68/100)+(I5*('Loading Loss'!I8/('Loading Loss'!I8+'Loading Loss'!I7))) -> 2.9154833 | M12: =D5*'Fuel Composition'!$J$11/100 -> 0.41412 | N12: =F5*'Fuel Composition'!$J$116/100 -> 9.6155021e-05 | O12: =(C5*'Fuel Composition'!$J$42/100)+(D5*'Fuel Composition'!$J$9/100)+(E5*'Fuel Composition'!$J$94/100)+(F5*'Fuel Composition'!$J$118/100)+(G5*'Fuel Composition'!$J$140/100)+('500000MP'!H5*'Fuel Composition'!$J$69/100) -> 0.68483109 | P12: =SUM(B12:O12) -> 35.991402
A13: Model Plant | B13: =AVERAGE(B11:B12) -> 3.689445 | C13: =AVERAGE(C11:C12) -> 3.656193e-05 | D13: =AVERAGE(D11:D12) -> 0.034268074 | E13: =AVERAGE(E11:E12) -> 0.0047502 | F13: =AVERAGE(F11:F12) -> 0.18823175 | G13: =AVERAGE(G11:G12) -> 0.0098810625 | H13: =AVERAGE(H11:H12) -> 9.6921606 | I13: =AVERAGE(I11:I12) -> 9.2764354 | ... O13: =AVERAGE(O11:O12) -> 0.519134 | P13: =SUM(B13:O13) -> 25.893705
B14: =B13/$P$13 -> 0.14248424 | C14: =C13/$P$13 -> 1.4120007e-06 | D14: =D13/$P$13 -> 0.0013234133 | E14: =E13/$P$13 -> 0.00018344999 | F14: =F13/$P$13 -> 0.0072694021 | G14: =G13/$P$13 -> 0.00038160095 | H14: =H13/$P$13 -> 0.37430567 | I14: =I13/$P$13 -> 0.3582506 | ... O14: =O13/$P$13 -> 0.020048657
A16: Average CE | B16: 0.97
A17: VOC Credit ($/ton) | B17: 672
A19: Total Hours Loading | B19: Hours Loading >1.5 psia
A20: =K3*1000/42/5000 -> 2380.9524 | B20: =SUM(C3,D3,H3,(0.5*J3),(0.5*I3))*1000/42/5000 -> 1076.1905
A21: Total Hours Operating (1.1 factor of safety + 100 startup hours)
A22: =A20*1.1+100 -> 2719.0476 | B22: =B20*1.1+100 -> 1283.8095
A24: lb VOC emitted /hr | C24: VOC Reduced (TPY)
A25: (based on gasoline)
A26: =D6*2000/(D3*1000/42/5000) -> 546 | C26: =B16*SUM(C6,D6,H6,(0.74*I6),J6) -> 264.47949
B28: Carbon Adsorber | M28: Thermal Oxidizer
B29: Costs (2023 dollars) | H29: HAP Emission Reductions (tpy) | I29: HAP Cost Effectiveness ($/ton) | J29: Incremental HAP Cost Effectiveness ($/ton) | M29: Costs (2023 dollars) | Q29: HAP Emission Reductions (tpy) | R29: HAP Cost Effectiveness ($/ton) | S29: Incremental HAP Cost Effectiveness ($/ton)
B30: Capital Costs | C30: Annual Operating Costs | D30: Annual Capital Recovery | E30: Total Annual Costs | F30: Solvent Recovery Credit | G30: Total Annual Costs with Credits | M30: Capital Costs | N30: Annual Operating Costs | O30: Annual Capital Recovery | P30: Total Annual Costs
A31: Typical MTVLO Facility | L31: Typical MTVLO Facility
A32: 1300 hrs (1.5 psia) | B32: 3686375 | C32: 343426 | D32: =E43*(B32-((1.08*E45*E46)+(E47*E46/E48))) -> 373972.32 | E32: =C32+D32 -> 717398.32 | F32: =VOC_Credit*Average_CE*SUM(C6,D6,H6,(0.74*I6),J6) -> 177730.22 | G32: =C32+D32-F32 -> 539668.1 | H32: =($P$13*Average_CE*SUM(C7,D7,H7,(0.74*I7),J7)) -> 24.993404 | I32: =G32/H32 -> 21592.421 | L32: 1300 hrs (1.5 psia) | M32: 447809 | N32: 288223 | O32: =M32*O43 -> 50731.044 | P32: =N32+O32 -> 338954.04 | Q32: =H32 -> 24.993404 | R32: =(N32+O32)/Q32 -> 13561.74
A33: 2725 hrs (no exemption) | B33: 3686375 | C33: 449379 | D33: =E43*(B33-((1.08*E45*E46)+(E47*E46/E48))) -> 373972.32 | E33: =C33+D33 -> 823351.32 | F33: =K6*VOC_Credit*Average_CE -> 178608.36 | G33: =C33+D33-F33 -> 644742.96 | H33: =$P$13*Average_CE -> 25.116894 | I33: =G33/H33 -> 25669.693 | J33: =(G33-G32)/(H33-H32) -> 850878.52 | L33: 2725 hrs (no exemption) | M33: 447809 | N33: 584525 | O33: =M33*O43 -> 50731.044 | P33: =N33+O33 -> 635256.04 | Q33: =H33 -> 25.116894 | R33: =(N33+O33)/Q33 -> 25291.983 | S33: =(N33+O33-N32-O32)/(Q33-Q32) -> 2399403.8
N34: TAC
A36: Assumptions:
A37: 1. Loading Rate = 5000 bbl/hr
A38: 2. Ships and Barges are loaded equally
A39: 3. Up to 1 vessel can be loaded at once
D42: = CRFAdsorber × (TCI - [(1.08 x CC x Mc) + (LR x Mc/CRR)] = | N42: =CRF x TCI
D43: CRF = | E43: =(E49*(1+E49)^15)/(((1+E49)^15)-1) -> 0.11328724 | F43: Capital Recovery Factor for adsorber vessels and auxiliary equipment | N43: CRF = | O43: =(O45*(1+O45)^15)/(((1+O45)^15)-1) -> 0.11328724
D44: TCI = | E44: =B32 -> 3686375 | F44: Total Capital Investment | N44: TCI = | O44: =M33 -> 447809
D45: CC = | E45: 5.56 | F45: Carbon Cost | N45: Interest Rate | O45: 0.075
D46: Mc = | E46: 62932 | F46: Carbon Consumption
D47: LR = | E47: 44.46 | F47: Labor Rate
D48: CRR = | E48: 379 | F48: (lb/hr) Carbon Replacement Rate
D49: Interest Rate | E49: 0.075

Sheet 5000000MP 
A1: Large Model Plant
C2: Crude Petroleum | D2: Gasoline | E2: Kerosene | F2: Distillate Fuel Oil | G2: Residual Fuel Oil | H2: Naphtha & Solvents | I2: Benzene & Toluene | J2: Alcohols | K2: Total
A3: Gallons Loaded (1000 gal/yr) | C3: 136000 | D3: 1929000 | E3: 620000 | F3: 1493000 | G3: 191000 | H3: 320000 | I3: 85000 | J3: 226000 | K3: =SUM(C3:J3) -> 5000000
A4: VOC Loading Loss (TPY) | B4: Ships | C4: =C3*'Loading Loss'!H20/2000 -> 62.76323 | D4: =D3*'Loading Loss'!B24/2000 -> 1736.1 | E4: =E3*'Loading Loss'!H4/2000 -> 1.8973705 | F4: =F3*'Loading Loss'!H5/2000 -> 3.9767175 | G4: =G3*'Loading Loss'!H6/2000 -> 0.34908402 | H4: =H3*'Loading Loss'!H3/2000 -> 987.85651 | I4: =I3*(AVERAGE('Loading Loss'!H7:H8))/2000 -> 19.675653 | J4: =J3*(AVERAGE('Loading Loss'!H9:H10))/2000 -> 15.884257 | K4: =SUM(C4:J4) -> 2828.5028
B5: Barges | C5: =C3*'Loading Loss'!H20/2000 -> 62.76323 | D5: =D3*'Loading Loss'!C24/2000 -> 3279.3 | E5: ='Loading Loss'!I4*'50000MP'!E3/2000 -> 0.0015332526 | F5: =F3*'Loading Loss'!I5/2000 -> 9.94179 | G5: =G3*'Loading Loss'!I6/2000 -> 0.87271051 | H5: =H3*'Loading Loss'!I3/2000 -> 2469.6413 | I5: =I3*(AVERAGE('Loading Loss'!I7:I8))/2000 -> 49.189133 | J5: =J3*(AVERAGE('Loading Loss'!I9:I10))/2000 -> 39.710644 | K5: =SUM(C5:J5) -> 5911.4203
B6: Model Plant | C6: =AVERAGE(C4:C5) -> 62.76323 | D6: =AVERAGE(D4:D5) -> 2507.7 | E6: =AVERAGE(E4:E5) -> 0.94945188 | F6: =AVERAGE(F4:F5) -> 6.9592537 | G6: =AVERAGE(G4:G5) -> 0.61089726 | H6: =AVERAGE(H4:H5) -> 1728.7489 | I6: =AVERAGE(I4:I5) -> 34.432393 | J6: =AVERAGE(J4:J5) -> 27.797451 | K6: =SUM(C6:J6) -> 4369.9616
A7: Percent of Total Loading Loss | C7: =C6/$K$6 -> 0.014362421 | D7: =D6/$K$6 -> 0.57384944 | E7: =E6/$K$6 -> 0.00021726779 | F7: =F6/$K$6 -> 0.0015925206 | G7: =G6/$K$6 -> 0.00013979465 | H7: =H6/$K$6 -> 0.39559819 | I7: =I6/$K$6 -> 0.0078793355 | J7: =J6/$K$6 -> 0.0063610286 | K7: =SUM(C7:J7) -> 1
A9: Large Model Plant Emissions
B10: Benzene (TPY) | C10: Biphenyl (TPY) | D10: Chlorine (TPY) | E10: Cumene (TPY) | F10: Ethylbenzene (TPY) | G10: Ethylene Glycol (TPY) | H10: Hexane (TPY) | I10: Methanol (TPY) | J10: Napthalene (TPY) | K10: Phenol (TPY) | L10: Toluene (TPY) | M10: 2,2,4-Trimethyl-pentane (isooctane) (TPY) | N10: Styrene (TPY) | O10: Xylene (TPY) | P10: Total HAP (TPY)
A11: Ships | B11: =(C4*'Fuel Composition'!$J$32/100)+(D4*'Fuel Composition'!$J$6/100)+(E4*'Fuel Composition'!$J$87/100)+(F4*'Fuel Composition'!$J$110/100)+(G4*'Fuel Composition'!$J$135/100)+(H4*'Fuel Composition'!$J$64/100)+(I4*('Loading Loss'!H9/('Loading Loss'!H9+'Loading Loss'!H10))) -> 42.545304 | C11: =(C4*'Fuel Composition'!$J$33/100)+(E4*'Fuel Composition'!$J$88/100)+(F4*'Fuel Composition'!$J$111/100) -> 8.1736935e-05 | D11: =G4*'Fuel Composition'!$J$137/100 -> 0.059937725 | E11: =D4*'Fuel Composition'!$J$12/100 -> 0.0729162 | F11: =(D4*'Fuel Composition'!$J$10/100)+(C4*'Fuel Composition'!$J$35/100)+(E4*'Fuel Composition'!$J$89/100)+(F4*'Fuel Composition'!$J$112/100)+(G4*'Fuel Composition'!$J$136/100)+(H4*'Fuel Composition'!$J$74/100) -> 2.123932 | G11: =J4*('Loading Loss'!H10/('Loading Loss'!H10+'Loading Loss'!H9)) -> 0.01690141 | H11: =(D4*'Fuel Composition'!$J$7/100)+(C4*'Fuel Composition'!$J$36/100)+(E4*'Fuel Composition'!$J$90/100)+(F4*'Fuel Composition'!$J$113/100)+(H4*'Fuel Composition'!$J$66/100) -> 83.219225 | I11: =J4*('Loading Loss'!H9/('Loading Loss'!H9+'Loading Loss'!H10)) -> 15.867356 | J11: =(D4*'Fuel Composition'!$J$13/100)+(C4*'Fuel Composition'!$J$37/100)+(E4*'Fuel Composition'!$J$91/100)+(F4*'Fuel Composition'!$J$114/100)+(G4*'Fuel Composition'!$J$138/100) -> 0.01027791 | K11: =(C4*'Fuel Composition'!$J$39/100)+(E4*'Fuel Composition'!$J$92/100)+(F4*'Fuel Composition'!$J$115/100) -> 0.0019557916 | L11: =(D4*'Fuel Composition'!$J$8/100)+(C4*'Fuel Composition'!$J$40/100)+(E4*'Fuel Composition'!$J$93/100)+(F4*'Fuel Composition'!$J$117/100)+(G4*'Fuel Composition'!$J$139/100)+(H4*'Fuel Composition'!$J$68/100)+(I4*('Loading Loss'!H8/('Loading Loss'!H8+'Loading Loss'!H7))) -> 27.541082 | M11: =D4*'Fuel Composition'!$J$11/100 -> 4.86108 | N11: =F4*'Fuel Composition'!$J$116/100 -> 0.00039767175 | O11: =(C4*'Fuel Composition'!$J$42/100)+(D4*'Fuel Composition'!$J$9/100)+(E4*'Fuel Composition'!$J$94/100)+(F4*'Fuel Composition'!$J$118/100)+(G4*'Fuel Composition'!$J$140/100)+(H4*'Fuel Composition'!$J$69/100) -> 6.6396791 | P11: =SUM(B11:O11) -> 182.96013
A12: Barges | B12: =(C5*'Fuel Composition'!$J$32/100)+(D5*'Fuel Composition'!$J$6/100)+(E5*'Fuel Composition'!$J$87/100)+(F5*'Fuel Composition'!$J$110/100)+(G5*'Fuel Composition'!$J$135/100)+(H5*'Fuel Composition'!$J$64/100)+(I5*('Loading Loss'!H10/('Loading Loss'!H10+'Loading Loss'!H11))) -> 97.61163 | C12: =(C5*'Fuel Composition'!$J$33/100)+(E5*'Fuel Composition'!$J$88/100)+(F5*'Fuel Composition'!$J$111/100) -> 6.2778562e-05 | D12: =G5*'Fuel Composition'!$J$137/100 -> 0.1498444 | E12: =D5*'Fuel Composition'!$J$12/100 -> 0.1377306 | F12: =(D5*'Fuel Composition'!$J$10/100)+(C5*'Fuel Composition'!$J$35/100)+(E5*'Fuel Composition'!$J$89/100)+(F5*'Fuel Composition'!$J$112/100)+(G5*'Fuel Composition'!$J$136/100)+(H5*'Fuel Composition'!$J$74/100) -> 4.5317393 | G12: =J5*('Loading Loss'!I10/('Loading Loss'!I10+'Loading Loss'!I9)) -> 0.04225409 | H12: =(D5*'Fuel Composition'!$J$7/100)+(C5*'Fuel Composition'!$J$36/100)+(E5*'Fuel Composition'!$J$90/100)+(F5*'Fuel Composition'!$J$113/100)+(H5*'Fuel Composition'!$J$66/100) -> 196.81888 | I12: =J5*('Loading Loss'!I9/('Loading Loss'!I10+'Loading Loss'!I9)) -> 39.66839 | J12: =(D5*'Fuel Composition'!$J$13/100)+(C5*'Fuel Composition'!$J$37/100)+(E5*'Fuel Composition'!$J$91/100)+(F5*'Fuel Composition'!$J$114/100)+(G5*'Fuel Composition'!$J$138/100) -> 0.017642499 | K12: =(C5*'Fuel Composition'!$J$39/100)+(E5*'Fuel Composition'!$J$92/100)+(F5*'Fuel Composition'!$J$115/100) -> 0.00062870557 | L12: =(D5*'Fuel Composition'!$J$8/100)+(C5*'Fuel Composition'!$J$40/100)+(E5*'Fuel Composition'!$J$93/100)+(F5*'Fuel Composition'!$J$117/100)+(G5*'Fuel Composition'!$J$139/100)+(H5*'Fuel Composition'!$J$68/100)+(I5*('Loading Loss'!I8/('Loading Loss'!I8+'Loading Loss'!I7))) -> 57.587315 | M12: =D5*'Fuel Composition'!$J$11/100 -> 9.18204 | N12: =F5*'Fuel Composition'!$J$116/100 -> 0.000994179 | O12: =(C5*'Fuel Composition'!$J$42/100)+(D5*'Fuel Composition'!$J$9/100)+(E5*'Fuel Composition'!$J$94/100)+(F5*'Fuel Composition'!$J$118/100)+(G5*'Fuel Composition'!$J$140/100)+('5000000MP '!H5*'Fuel Composition'!$J$69/100) -> 13.188061 | P12: =SUM(B12:O12) -> 418.93721
A13: Model Plant | B13: =AVERAGE(B11:B12) -> 70.078467 | C13: =AVERAGE(C11:C12) -> 7.2257748e-05 | D13: =AVERAGE(D11:D12) -> 0.10489106 | E13: =AVERAGE(E11:E12) -> 0.1053234 | F13: =AVERAGE(F11:F12) -> 3.3278357 | G13: =AVERAGE(G11:G12) -> 0.02957775 | H13: =AVERAGE(H11:H12) -> 140.01905 | I13: =AVERAGE(I11:I12) -> 27.767873 | ... O13: =AVERAGE(O11:O12) -> 9.9138703 | P13: =SUM(B13:O13) -> 300.94867
A15: Average CE | B15: 0.97
A16: VOC Credit ($/ton) | B16: 672
A18: Hours Loading | B18: Vessels Loading Simultaneously | C18: Hours Loading Per Vessel | D18: Hours Loading >1.5 psia | E18: Vessels Loading Simultaneously | F18: Hours Loading Per Vessel >1.5 psia
A19: =K3*1000/42/5000 -> 23809.524 | B19: =A19/8760 -> 2.7179822 | C19: =2.62/3*8760 -> 7650.4 | D19: =SUM(C3,D3,H3,(0.5*J3),(0.5*I3))*1000/42/5000 -> 12097.619 | E19: =D19/8760 -> 1.3810067 | F19: =1.33/2*8760 -> 5825.4
C20: Total Hours Operating (1.1 factor of safety + 100 startup hours)
C21: =C19*1.1+100 -> 8515.44 | F21: =F19*1.1+100 -> 6507.94
A24: lb VOC emitted /hr | B24: lb VOC/hr | D24: VOC Reduced (TPY)
A25: (based on gasoline) | B25: (assumes 2 loading simultaneously)
A26: =D6*2000/(D3*1000/42/5000) -> 546 | B26: =A26*2 -> 1092 | D26: =B15*SUM(C6,D6,H6,(0.74*I6),J6) -> 4221.9149
B28: Carbon Adsorber | M28: Thermal Oxidizer
B29: Costs (2023 dollars) | H29: HAP Emission Reductions (tpy) | I29: HAP Cost Effectiveness ($/ton) | J29: Incremental HAP Cost Effectiveness ($/ton) | M29: Costs (2023 dollars) | Q29: HAP Emission Reductions (tpy) | R29: HAP Cost Effectiveness ($/ton) | S29: Incremental HAP Cost Effectiveness ($/ton)
B30: Capital Costs | C30: Annual Operating Costs | D30: Annual Capital Recovery | E30: Total Annual Costs | F30: Solvent Recovery Credit | G30: Total Annual Costs with Credits | M30: Capital Costs | N30: Annual Operating Costs | O30: Annual Capital Recovery | P30: Total Annual Costs
A31: Typical MTVLO Facility | L31: Typical MTVLO Facility
A32: 6525 hrs (1.5 psia) | B32: =3686375*2 -> 7372750 | C32: =731920*2 -> 1463840 | D32: =E43*(B32-((1.08*E45*E46)+(E47*E46/E48))) -> 791591.56 | E32: =C32+D32 -> 2255431.6 | F32: =VOC_Credit*Average_CE*SUM(C6,D6,H6,(0.74*I6),J6) -> 2837126.8 | G32: =C32+D32-F32 -> -581695.23 | H32: =($P$13*Average_CE*SUM(C7,D7,H7,(0.74*I7),J7)) -> 290.75305 | I32: =G32/H32 -> -2000.6505 | L32: 6525 hrs (1.5 psia) | M32: =447809*2 -> 895618 | N32: =1374664*2 -> 2749328 | O32: =M32*O43 -> 101462.09 | P32: =N32+O32 -> 2850790.1 | Q32: =H32 -> 290.75305 | R32: =(N32+O32)/Q32 -> 9804.8501
A33: 8525 hrs (no exemption) | B33: =3686375*3 -> 11059125 | C33: =880626*3 -> 2641878 | D33: =E43*(B33-((1.08*E45*E46)+(E47*E46/E48))) -> 1209210.8 | E33: =C33+D33 -> 3851088.8 | F33: =K6*VOC_Credit*Average_CE -> 2848515.8 | G33: =C33+D33-F33 -> 1002573 | H33: =$P$13*Average_CE -> 291.92021 | I33: =G33/H33 -> 3434.4078 | J33: =(G33-G32)/(H33-H32) -> 1357372.1 | L33: 8525 hrs (no exemption) | M33: =447809*3 -> 1343427 | N33: =1788447*3 -> 5365341 | O33: =M33*O43 -> 152193.13 | P33: =N33+O33 -> 5517534.1 | Q33: =H33 -> 291.92021 | R33: =(N33+O33)/Q33 -> 18900.83 | S33: =(N33+O33-N32-O32)/(Q33-Q32) -> 2284817.6
A36: Assumptions:
A37: 1. Loading Rate = 5000 bbl/hr
A38: 2. Ships and Barges are loaded equally
A39: 3. Up to 2 vessels can be loaded at once
A40: 4. Costs assume two control systems are required
D42: = CRFAdsorber × (TCI - [(1.08 x CC x Mc) + (LR x Mc/CRR)] = | N42: =CRF x TCI
D43: CRF = | E43: =(E49*(1+E49)^15)/(((1+E49)^15)-1) -> 0.11328724 | F43: Capital Recovery Factor for adsorber vessels and auxiliary equipment | N43: CRF = | O43: =(O45*(1+O45)^15)/(((1+O45)^15)-1) -> 0.11328724
D44: TCI = | E44: =B32 -> 7372750 | F44: Total Capital Investment | N44: TCI = | O44: =M32 -> 895618
D45: CC = | E45: 5.56 | F45: Carbon Cost | N45: Interest Rate | O45: 0.075
D46: Mc = | E46: 62932 | F46: Carbon Consumption
D47: LR = | E47: 44.46 | F47: Labor Rate
D48: CRR = | E48: 379 | F48: (lb/hr) Carbon Replacement Rate
D49: Interest Rate | E49: 0.075

Sheet Loading Loss
A1: Commodities | B1: Saturation Factor (S) | C1: Saturation Factor (S) | D1: True Vapor Pressure (P) | E1: Molecular Weight | F1: Temperature | G1: Density | H1: Loading Loss (ships) | I1: Loading Loss (Barges) | L1: Reid Vapor Pressure | M1: Loading Loss (ships) | N1: Loading Loss (Barges) | O1: Average Loading Loss
B2: ships | C2: barges | D2: psia | E2: lb/lb-mole | F2: °R | G2: lb/gal | H2: lb/1000 gal | I2: lb/1000 gal | L2: psia | M2: lb/hr | N2: lb/hr | O2: lb/hr
A3: Naptha and Solvents | B3: 0.2 | C3: 0.5 | D3: 10.2 | E3: 128.1705 | F3: 527.67 | G3: 5.55 | H3: 6.1741032 | I3: 15.435258 | L3: 13 | M3: 735.01229 | N3: 1837.5307 | O3: =AVERAGE(M3:N3) -> 1286.2715
A4: Kerosene | B4: 0.2 | C4: 0.5 | D4: 0.1 | E4: 162 | F4: 527.67 | G4: 6.82 | H4: 0.00612055 | I4: 0.01530138 | L4: 9 | M4: 0.72863722 | N4: 1.821593 | O4: =AVERAGE(M4:N4) -> 1.2751151
A5: Distillate Oil No. 2 | B5: 0.2 | C5: 0.5 | D5: 0.006 | E5: 188 | F5: 527.67 | G5: 7 | H5: 0.00532715 | I5: 0.01331787 | L5: 0.1 | M5: 0.63418424 | N5: 1.5854606 | O5: =AVERAGE(M5:N5) -> 1.1098224
A6: Residual Oil No. 6 | B6: 0.2 | C6: 0.5 | D6: 0.002 | E6: 387 | F6: 527.67 | G6: 8.3 | H6: 0.00365533 | I6: 0.00913833 | L6: 0.1 | M6: 0.43515834 | N6: 1.0878958 | O6: =AVERAGE(M6:N6) -> 0.76152709
A7: Benzene | B7: 0.2 | C7: 0.5 | D7: 1.86 | E7: 78.112 | F7: 527.67 | G7: 7.29 | H7: 0.68614568 | I7: 1.7153642 | J7: =I7/(I7+I8) -> 0.74104761 | L7: 1.4 | M7: 81.68401 | N7: 204.21003 | O7: =AVERAGE(M7:N7) -> 142.94702 | R7: 0.941215 | S7: 2.353037 | T7: =AVERAGE(R7:S7) -> 1.647126
A8: Toluene | B8: 0.2 | C8: 0.5 | D8: 0.551 | E8: 92.141 | F8: 527.67 | G8: 7.2 | H8: 0.23976741 | I8: 0.59941853 | L8: 1.1 | M8: 28.54374 | N8: 71.359349 | O8: =AVERAGE(M8:N8) -> 49.951544 | R8: 0.33301 | S8: 0.832526 | T8: =AVERAGE(R8:S8) -> 0.582768
A9: Methanol | B9: 0.2 | C9: 0.5 | D9: 1.856 | E9: 32.04 | F9: 527.67 | G9: 6.6 | H9: 0.28083816 | I9: 0.70209539 | J9: =I9/(I9+I10) -> 0.99893595 | L9: 1.8 | M9: 33.433114 | N9: 83.582785 | O9: =AVERAGE(M9:N9) -> 58.507949 | R9: 0.425512 | S9: 1.063781 | T9: =AVERAGE(R9:S9) -> 0.7446465
A10: Ethylene glycol | B10: 0.2 | C10: 0.5 | D10: 0.00102 | E10: 62.1 | F10: 527.67 | G10: 9.15 | H10: 0.00029914 | I10: 0.00074786 | L10: 0.01 | M10: 0.03561214 | N10: 0.08903036 | O10: =AVERAGE(M10:N10) -> 0.06232125 | R10: 0.000327 | S10: 0.000817 | T10: =AVERAGE(R10:S10) -> 0.000572
M13: *assume 5000 bbl/hr
B14: True Vapor Pressure (P) | C14: Molecular Weight | D14: Temperature | E14: Vapor Growth Factor | F14: CG | G14: Density | H14: Arrival Emission Factor (uncleaned) | I14: Arrival Emisson Factor (ballasted) | J14: Arrival Emisson Factor (cleaned or gas-freed)
B15: psia | C15: lb/lb-mole | D15: °R | G15: lb/gal | H15: lb/1000 gal | I15: lb/1000 gal | J15: lb/1000 gal
A16: Crude Oil (RVP5) | B16: 3.36 | C16: 60 | D16: 527.67 | E16: 1.02 | F16: =1.84*(0.44*B16-0.42)*C16*E16/D16 -> 0.22586902 | G16: 7.21 | H16: 0.86 | I16: 0.46 | J16: 0.33
H17: Loading Loss (uncleaned) | I17: Loading Loss (Ballasted) | J17: Loading Loss (cleaned or gas-freed) | M17: Loading Loss (uncleaned) | N17: Loading Loss (Ballasted) | O17: Loading Loss (cleaned or gas-freed)
H18: lb/1000 gal | I18: lb/1000 gal | J18: lb/1000 gal | M18: lb/hr | N18: lb/hr | O18: lb/hr
H19: =H16+$F16 -> 1.085869 | I19: =I16+$F16 -> 0.68586902 | J19: =J16+$F16 -> 0.55586902 | L19: 5 | M19: 287.77633 | N19: 240.15728 | O19: 224.68109
G20: Total VOC lossed (assuming 15% is methane and ethane): | H20: =0.85*H19 -> 0.92298867
B22: Loading Loss (ships) | C22: Loading Loss (Barges) | D22: Density | M22: Loading Loss (ships) | N22: Loading Loss (Barges)
B23: lb/1000 gal | C23: lb/1000 gal | D23: lb/gal | M23: lb/hr | N23: lb/hr
A24: Gasoline | B24: 1.8 | C24: 3.4 | D24: 6.26 | L24: 6 | M24: 214.28571 | N24: 404.76191 | O24: =AVERAGE(M24:N24) -> 309.52381

Sheet Fuel Composition
A2: API PERF data - Reformulated Gasoline (added Ethanol)
D3: wt%/wt frac liq | E3: n liq | F3: x | H3: y | J3: wt frac vapor | O3: Antoine Eqn coefficients
B4: MW | C4: VP, pure component, psia | D4: Gasoline, Liquid, wt% | E4: Gasoline, Liquid, moles | F4: Gasoline, Liquid, mole frac | G4: Gasoline, Partial Pressure, Pi, psia | H4: Gasoline, Vapor, mole frac | I4: Avg MW vapor = y(i)*MW(i) | J4: Gasoline, Vapor, wt% | L4: T = | M4: 68 | N4: F | O4: A | P4: B | Q4: C | T4: Ships | U4: Barges
M5: 20 | N5: C | T5: ppm | U5: ppm
A6: Benzene | B6: 78.11 | C6: 1.454 | D6: 1.61 | E6: 0.000206 | F6: 0.0173 | G6: 0.0252 | H6: 0.00672 | I6: 0.525 | J6: 0.8 | O6: 6.90565 | P6: 1211.033 | Q6: 220.79 | T6: 2.29 | U6: 4.33 | V6: =AVERAGE(T6:U6) -> 3.31
A7: Hexane | B7: 86.18 | C7: 2.347 | D7: 1 | E7: 0.000116 | F7: 0.00976 | G7: 0.0229 | H7: 0.00611 | I7: 0.527 | J7: 0.8 | O7: 6.87601 | P7: 1171.17 | Q7: 224.41 | T7: 2.3 | U7: 4.34 | V7: =AVERAGE(T7:U7) -> 3.32
A8: Toluene | B8: 92.14 | C8: 0.422 | D8: 7.2 | E8: 0.000783 | F8: 0.0658 | G8: 0.0278 | H8: 0.00742 | I8: 0.684 | J8: 1.04 | O8: 6.95464 | P8: 1344.8 | Q8: 219.48 | T8: 2.98 | U8: 5.63 | V8: =AVERAGE(T8:U8) -> 4.305
A9: Xylene | B9: 106.14 | C9: 0.126 | D9: 7.17 | E9: 0.000676 | F9: 0.0568 | G9: 0.00716 | H9: 0.00191 | I9: 0.203 | J9: 0.31 | O9: 6.99052 | P9: 1453.43 | Q9: 215.31 | T9: 0.88 | U9: 1.67 | V9: =AVERAGE(T9:U9) -> 1.275
A10: Ethylbenzene | B10: 106.17 | C10: 0.137 | D10: 1.605 | E10: 0.000151 | F10: 0.0127 | G10: 0.00174 | H10: 0.000465 | I10: 0.0493 | J10: 0.07 | O10: 6.95719 | P10: 1424.255 | Q10: 213.21 | T10: 0.22 | U10: 0.41 | V10: =AVERAGE(T10:U10) -> 0.315
A11: 2,2,4-Trimethylpentane (isooctane) | B11: 114.23 | C11: 0.747 | D11: 1.098 | E11: 9.61e-05 | F11: 0.00808 | G11: 0.00604 | H11: 0.00161 | I11: 0.184 | J11: 0.28 | O11: 6.81189 | P11: 1257.84 | Q11: 220.74 | T11: 0.8 | U11: 1.52 | V11: =AVERAGE(T11:U11) -> 1.16
A12: Cumene | B12: 120.19 | C12: 0.065 | D12: 0.19 | E12: 1.58e-05 | F12: 0.00133 | G12: 8.58e-05 | H12: 2.29e-05 | I12: 0.00275 | J12: 0.0042 | O12: 6.93666 | P12: 1460.793 | Q12: 207.78 | T12: 0.01 | U12: 0.02 | V12: =AVERAGE(T12:U12) -> 0.015
A13: Naphthalene | B13: 128.17 | C13: 0.003 | D13: 0.444 | E13: 3.46e-05 | F13: 0.00291 | G13: 1.02e-05 | H13: 2.72e-06 | I13: 0.000348 | J13: 0.0005 | O13: 7.37 | P13: 1968.36 | Q13: 222.61 | T13: 0 | U13: 0 | V13: =AVERAGE(T13:U13) -> 0
A14: Ethanol | B14: 46.07 | C14: 0.897 | D14: 8 | E14: 0.00174 | F14: 0.146 | G14: 0.131 | H14: 0.035 | I14: 1.61 | J14: 2.4442 | O14: 8.2109 | P14: 1718.1 | Q14: 237.52 | T14: 7.03 | U14: 13.28 | V14: =AVERAGE(T14:U14) -> 10.155
A15: n-Butane | B15: 58.12 | C15: 30.076 | D15: 4.7 | E15: 0.000809 | F15: 0.068 | G15: 2.05 | H15: 0.546 | I15: 31.7 | J15: 48.16 | O15: 6.80896 | P15: 935.86 | Q15: 238.73 | T15: 138.49 | U15: 261.59 | V15: =AVERAGE(T15:U15) -> 200.04
A16: Isobutane | B16: 58.12 | C16: 11.103 | D16: 1.7 | E16: 0.000292 | F16: 0.0246 | G16: 0.273 | H16: 0.0729 | I16: 4.24 | J16: 6.43 | O16: 6.83315 | P16: 1040.73 | Q16: 235.45 | T16: 18.49 | U16: 34.93 | V16: =AVERAGE(T16:U16) -> 26.71
A17: Pentane | B17: 72.15 | C17: 8.524 | D17: 3.9 | E17: 0.000541 | F17: 0.0455 | G17: 0.387 | H17: 0.103 | I17: 7.46 | J17: 11.33 | O17: 6.85296 | P17: 1064.84 | Q17: 233.01 | T17: 32.57 | U17: 61.52 | V17: =AVERAGE(T17:U17) -> 47.045
... A23: Other VOC (assume Heptane is the surrogate for Other VOC) | B23: 100.2 | C23: 0.685 | D23: 25.68 | E23: 0.00256 | F23: 0.216 | G23: 0.148 | H23: 0.0394 | I23: 3.95 | J23: 5.99 | O23: 6.89677 | P23: 1264.9 | Q23: 216.54 | T23: 17.23 | U23: 32.55 | V23: =AVERAGE(T23:U23) -> 24.89
D25: 100 | E25: 0.01189096 | F25: 1 | G25: 3.75 | H25: 1 | I25: 65.88 | J25: 100
D26: 20.33 | G26: Total VP of mixture
D27: wt%HAP in liq | H27: 1 | J27: 3.3 | K27: HAP only %
B30: MW | C30: VP, pure component, psia | D30: Crude Oil, Liquid, wt% | E30: Crude Oil, Liquid, moles | F30: Crude Oil, Liquid, mole frac | G30: Crude Oil, Partial Pressure, Pi, psia | H30: Crude Oil, Vapor, mole frac | I30: Avg MW vapor = y(i)*MW(i) | J30: Crude Oil, Vapor, wt% | L30: T = | M30: 68 | N30: F | O30: A | P30: B | Q30: C | T30: Uncleaned | U30: Ballasted | V30: Cleaned or gas-freed
M31: 20 | N31: C | T31: ppm | U31: ppm | V31: ppm
A32: Benzene | B32: 78.11 | C32: 1.454 | D32: 0.446 | E32: 5.7099e-05 | F32: 0.00548 | G32: 0.00797 | H32: 0.00303 | I32: 0.237 | J32: 0.33 | O32: 6.90565 | P32: 1211.033 | Q32: 220.79 | T32: 1.0917148 | U32: 0.9110661 | V32: 0.852355
A33: Biphenyl | B33: 154.21 | C33: 0 | D33: 0.6 | E33: 3.89085e-05 | F33: 0.00373 | G33: 1.35e-06 | H33: 5.14e-07 | I33: 7.92e-05 | J33: 0.0001 | O33: 7.2454 | P33: 1998.72 | Q33: 202.74 | T33: 0.0003654 | U33: 0.0003049 | V33: 0.000285
A34: Cyclohexane | B34: 84.16 | C34: 1.499 | D34: 0.7 | E34: 8.31729e-05 | F34: 0.00798 | G34: 0.012 | H34: 0.00455 | I34: 0.383 | J34: 0.53 | O34: 6.8413 | P34: 1201.531 | Q34: 222.647 | T34: 1.7667404 | U34: 1.4743936 | V34: 1.379381
A35: Ethylbenzene | B35: 106.17 | C35: 0.137 | D35: 0.346 | E35: 3.25892e-05 | F35: 0.00313 | G35: 0.000428 | H35: 0.000163 | I35: 0.0173 | J35: 0.02 | O35: 6.95719 | P35: 1424.255 | Q35: 213.21 | T35: 0.0797312 | U35: 0.0665378 | V35: 0.06225
A36: n-Hexane | B36: 86.18 | C36: 2.347 | D36: 2.463 | E36: 0.000285797 | F36: 0.0274 | G36: 0.0644 | H36: 0.0245 | I36: 2.11 | J36: 2.9 | O36: 6.87601 | P36: 1171.17 | Q36: 224.41 | T36: 9.7317114 | U36: 8.1213815 | V36: 7.598024
A37: Naphthalene | B37: 128.17 | C37: 0.003 | D37: 0.219 | E37: 1.70867e-05 | F37: 0.00164 | G37: 5.72e-06 | H37: 2.18e-06 | I37: 0.000279 | J37: 0.0004 | O37: 7.37 | P37: 1968.36 | Q37: 222.61 | T37: 0.0012874 | U37: 0.0010744 | V37: 0.001005
A38: PAC (Thiophene used as surrogate) | B38: 84.14 | C38: 1.21 | D38: 0.0004 | E38: 4.75398e-08 | F38: 4.56e-06 | G38: 5.52e-06 | H38: 2.1e-06 | I38: 0.000177 | J38: 0.0002 | O38: 6.95926 | P38: 1246.02 | Q38: 221.35 | T38: 0.000815 | U38: 0.0006801 | V38: 0.000636
A39: Phenol | B39: 94.11 | C39: 0.004 | D39: 0.323 | E39: 3.43211e-05 | F39: 0.00329 | G39: 1.4e-05 | H39: 5.33e-06 | I39: 0.000502 | J39: 0.001 | O39: 7.1345 | P39: 1516.07 | Q39: 174.57 | T39: 0.0023139 | U39: 0.001931 | V39: 0.001807
A40: Toluene | B40: 92.14 | C40: 0.422 | D40: 0.878 | E40: 9.52898e-05 | F40: 0.00914 | G40: 0.00386 | H40: 0.00147 | I40: 0.135 | J40: 0.19 | O40: 6.95464 | P40: 1344.8 | Q40: 219.48 | T40: 0.6239852 | U40: 0.5207329 | V40: 0.487176
A41: 1,2,4-Trimethylbenzene | B41: 120.19 | C41: 0.028 | D41: 0.326 | E41: 2.71237e-05 | F41: 0.0026 | G41: 7.28e-05 | H41: 2.77e-05 | I41: 0.00333 | J41: 0.005 | O41: 7.04383 | P41: 1573.267 | Q41: 208.564 | T41: 0.0153575 | U41: 0.0128163 | V41: 0.01199
A42: Xylene | B42: 106.14 | C42: 0.126 | D42: 1.42 | E42: 0.000133786 | F42: 0.0128 | G42: 0.00162 | H42: 0.000615 | I42: 0.0653 | J42: 0.09 | O42: 6.99052 | P42: 1453.43 | Q42: 215.31 | T42: 0.3010841 | U42: 0.251263 | V42: 0.235071
A43: n-Butane | B43: 58.12 | C43: 30.076 | D43: 2.5 | E43: 0.000430145 | F43: 0.0413 | G43: 1.24 | H43: 0.472 | I43: 27.4 | J43: 37.75 | O43: 6.80896 | P43: 935.86 | Q43: 238.73 | T43: 126.564 | U43: 105.62115 | V43: 98.81472
... A46: Other VOC/Heptane Plus (assume Heptane is the surrogate for Other VOC) | B46: 100.2 | C46: 0.685 | D46: 80.7786 | E46: 0.008061737 | F46: 0.773 | G46: 0.53 | H46: 0.202 | I46: 20.2 | J46: 27.78 | O46: 6.89677 | P46: 1264.9 | Q46: 216.54 | T46: 93.13146 | U46: 77.720771 | V46: 72.7123
D48: 100 | E48: 0.01 | F48: 1 | G48: 2.63 | H48: 1 | I48: 72.7 | J48: 100
G50: 0.0782 | J50: 3.53 | K50: HAP only %
C51: Crude Oil True Vapor Pressure:
C52: 5.762
A54: EPCRA Section 313 Industry Guidance for Petroleum Terminals and Bulk Storage Facilities | O54: Antoine coefficient table | PDF
A56: Crude oil Composition and Properties | Download Table
B59: MW | C59: VP, pure component, psia | D59: Naphtha, Liquid, wt% | E59: Naphtha, Liquid, moles | F59: Naphtha, Liquid, mole frac | G59: Naphtha, Partial Pressure, Pi, psia | H59: Naphtha, Vapor, mole frac | I59: Avg MW vapor = y(i)*MW(i) | J59: Naphtha, Vapor, wt% | L59: T = | M59: 68 | N59: F | O59: A | P59: B | Q59: C | T59: Ships | U59: Barges
M60: 20 | N60: C | T60: ppm | U60: ppm
A61: n-Butane | B61: 58.12 | C61: 30.076 | D61: 1.5 | E61: 0.000258087 | F61: 0.024 | G61: 0.721 | H61: 0.199 | I61: 11.5 | J61: 15.35 | O61: 6.80896 | P61: 935.86 | Q61: 238.73 | T61: 170.75869 | U61: 426.89674 | V61: =AVERAGE(T61:U61) -> 298.82772
A62: Pentane | B62: 72.15 | C62: 8.524 | D62: 14.6 | E62: 0.002023562 | F62: 0.188 | G62: 1.6 | H62: 0.441 | I62: 31.9 | J62: 42.35 | O62: 6.85296 | P62: 1064.84 | Q62: 233.01 | T62: 471.07152 | U62: 1177.6788 | V62: =AVERAGE(T62:U62) -> 824.37516
A63: Cyclopentane | B63: 70.1 | C63: 5.022 | D63: 1.5 | E63: 0.00021398 | F63: 0.0199 | G63: 0.0999 | H63: 0.0275 | I63: 1.93 | J63: 2.56 | O63: 6.88676 | P63: 1124.162 | Q63: 231.361 | T63: 28.510961 | U63: 71.277403 | V63: =AVERAGE(T63:U63) -> 49.894182
A64: Benzene | B64: 78.11 | C64: 1.454 | D64: 1.8 | E64: 0.000230444 | F64: 0.0214 | G64: 0.0311 | H64: 0.00858 | I64: 0.67 | J64: 0.89 | O64: 6.90565 | P64: 1211.033 | Q64: 220.79 | T64: 9.9075946 | U64: 24.768986 | V64: =AVERAGE(T64:U64) -> 17.33829
A65: Cyclohexane | B65: 84.16 | C65: 1.499 | D65: 7.5 | E65: 0.000891139 | F65: 0.0828 | G65: 0.124 | H65: 0.0342 | I65: 2.88 | J65: 3.83 | O65: 6.8413 | P65: 1201.531 | Q65: 222.647 | T65: 42.56546 | U65: 106.41365 | V65: =AVERAGE(T65:U65) -> 74.489555
A66: n-Hexane | B66: 86.18 | C66: 2.347 | D66: 8.5 | E66: 0.000986308 | F66: 0.0917 | G66: 0.215 | H66: 0.0593 | I66: 5.11 | J66: 6.79 | O66: 6.87601 | P66: 1171.17 | Q66: 224.41 | T66: 75.520544 | U66: 188.80136 | V66: =AVERAGE(T66:U66) -> 132.16095
A67: 2-Methylhexane (surrogate for hexanes) | B67: 100.2 | C67: 3.316 | D67: 6.5 | E67: 0.000648703 | F67: 0.0603 | G67: 0.2 | H67: 0.0551 | I67: 5.52 | J67: 7.33 | O67: 6.8391 | P67: 1135.41 | Q67: 226.57 | T67: 81.593704 | U67: 203.98426 | V67: =AVERAGE(T67:U67) -> 142.78898
A68: Toluene | B68: 92.14 | C68: 0.422 | D68: 3 | E68: 0.000325591 | F68: 0.0303 | G68: 0.0128 | H68: 0.00352 | I68: 0.324 | J68: 0.43 | O68: 6.95464 | P68: 1344.8 | Q68: 219.48 | T68: 4.794269 | U68: 11.985673 | V68: =AVERAGE(T68:U68) -> 8.389971
A69: Xylene | B69: 106.14 | C69: 0.126 | D69: 2.8 | E69: 0.000263803 | F69: 0.0245 | G69: 0.00309 | H69: 0.00085 | I69: 0.0903 | J69: 0.12 | O69: 6.99052 | P69: 1453.43 | Q69: 215.31 | T69: 1.3349926 | U69: 3.3374814 | V69: =AVERAGE(T69:U69) -> 2.336237
A70: Heptane | B70: 100.2 | C70: 0.685 | D70: 4.4 | E70: 0.000439122 | F70: 0.0408 | G70: 0.028 | H70: 0.0077 | I70: 0.771 | J70: 1.03 | O70: 6.89677 | P70: 1264.9 | Q70: 216.54 | T70: 11.407071 | U70: 28.517677 | V70: =AVERAGE(T70:U70) -> 19.962374
A71: 2-Methylpentane (surrogate for C6 cpds) | B71: 86.18 | C71: 3.316 | D71: 14.9 | E71: 0.001728939 | F71: 0.161 | G71: 0.533 | H71: 0.147 | I71: 12.6 | J71: 16.81 | O71: 6.8391 | P71: 1135.41 | Q71: 226.57 | T71: 187.03787 | U71: 467.59469 | V71: =AVERAGE(T71:U71) -> 327.31628
A72: 2,3,4-Trimethylpentane (surrogate for C8 cpds) | B72: 114.23 | C72: 0.402 | D72: 16.8 | E72: 0.001470717 | F72: 0.137 | G72: 0.0549 | H72: 0.0151 | I72: 1.73 | J72: 2.3 | O72: 6.85396 | P72: 1315.08 | Q72: 217.53 | T72: 25.541775 | U72: 63.854437 | V72: =AVERAGE(T72:U72) -> 44.698106
... A75: Decane | B75: 142.29 | C75: 0.023 | D75: 7 | E75: 0.000491953 | F75: 0.0457 | G75: 0.00105 | H75: 0.000289 | I75: 0.0411 | J75: 0.05 | O75: 7.44 | P75: 1843.12 | Q75: 230.22 | T75: 0.6075213 | U75: 1.5188033 | V75: =AVERAGE(T75:U75) -> 1.0631623
D77: 100 | E77: 0.01 | F77: 1 | G77: 3.63 | H77: 1 | I77: 75.22 | J77: 100
G79: 0.265 | J79: 8.32 | K79: HAP only %
A81: 1. Typical composition of a naphtha feed containing 10 wt% aromatics [DSM] | Download Table
B85: MW | C85: VP, pure component, psia | D85: Kerosene, Liquid, wt% | E85: Kerosene, Liquid, moles | F85: Kerosene, Liquid, mole frac | G85: Kerosene, Partial Pressure, Pi, psia | H85: Kerosene, Vapor, mole frac | I85: Avg MW vapor = y(i)*MW(i) | J85: Kerosene, Vapor, wt% | L85: T = | M85: 68 | N85: F | O85: A | P85: B | Q85: C | T85: Ships | U85: Barges
M86: 20 | N86: C | T86: ppm | U86: ppm
A87: Benzene | B87: 78.11 | C87: 1.454 | D87: 0.004 | E87: 5.12098e-07 | F87: 6.63e-05 | G87: 9.64e-05 | H87: 0.00181 | I87: 0.141 | J87: 0.12 | O87: 6.90565 | P87: 1211.033 | Q87: 220.79 | T87: 0.0010539 | U87: 0.0026346 | V87: =AVERAGE(T87:U87) -> 0.00184425
A88: Biphenyl | B88: 154.21 | C88: 0 | D88: 0.12 | E88: 7.78171e-06 | F88: 0.00101 | G88: 3.64e-07 | H88: 6.84e-06 | I88: 0.00105 | J88: 0.001 | O88: 7.2454 | P88: 1998.72 | Q88: 202.74 | T88: 7.866e-06 | U88: 1.966e-05 | V88: =AVERAGE(T88:U88) -> 1.3763e-05
A89: Ethylbenzene | B89: 106.17 | C89: 0.137 | D89: 0.127 | E89: 1.19619e-05 | F89: 0.00155 | G89: 0.000212 | H89: 0.00398 | I89: 0.422 | J89: 0.35 | O89: 6.95719 | P89: 1424.255 | Q89: 213.21 | T89: 0.0031499 | U89: 0.0078748 | V89: =AVERAGE(T89:U89) -> 0.00551235
A90: n-Hexane | B90: 86.18 | C90: 2.347 | D90: 0.005 | E90: 5.80181e-07 | F90: 7.51e-05 | G90: 0.000176 | H90: 0.00331 | I90: 0.285 | J90: 0.24 | O90: 6.87601 | P90: 1171.17 | Q90: 224.41 | T90: 0.0021264 | U90: 0.005316 | V90: =AVERAGE(T90:U90) -> 0.0037212
A91: Naphthalene | B91: 128.17 | C91: 0.003 | D91: 0.733 | E91: 5.71897e-05 | F91: 0.0074 | G91: 2.58e-05 | H91: 0.000485 | I91: 0.0622 | J91: 0.05 | O91: 7.37 | P91: 1968.36 | Q91: 222.61 | T91: 0.0004638 | U91: 0.0011595 | V91: =AVERAGE(T91:U91) -> 0.00081165
A92: Phenol | B92: 94.11 | C92: 0.004 | D92: 0.77 | E92: 8.18181e-05 | F92: 0.0106 | G92: 4.51e-05 | H92: 0.000846 | I92: 0.0796 | J92: 0.07 | O92: 7.1345 | P92: 1516.07 | Q92: 174.57 | T92: 0.0005937 | U92: 0.0014843 | V92: =AVERAGE(T92:U92) -> 0.001039
A93: Toluene | B93: 92.14 | C93: 0.422 | D93: 0.13 | E93: 1.4109e-05 | F93: 0.00183 | G93: 0.000771 | H93: 0.0145 | I93: 1.33 | J93: 1.11 | O93: 6.95464 | P93: 1344.8 | Q93: 219.48 | T93: 0.0099442 | U93: 0.0248605 | V93: =AVERAGE(T93:U93) -> 0.01740235
A94: Xylene | B94: 106.14 | C94: 0.126 | D94: 0.31 | E94: 2.92067e-05 | F94: 0.00378 | G94: 0.000476 | H94: 0.00894 | I94: 0.948 | J94: 0.79 | O94: 6.99052 | P94: 1453.43 | Q94: 215.31 | T94: 0.0070747 | U94: 0.0176867 | V94: =AVERAGE(T94:U94) -> 0.0123807
A95: Heptane | B95: 100.2 | C95: 0.685 | D95: 0.08 | E95: 7.98403e-06 | F95: 0.00103 | G95: 0.000708 | H95: 0.0133 | I95: 1.33 | J95: 1.11 | O95: 6.89677 | P95: 1264.9 | Q95: 216.54 | T95: 0.0099274 | U95: 0.0248186 | V95: =AVERAGE(T95:U95) -> 0.017373
A96: 2,3,4-Trimethylpentane (surrogate for C8 cpds) | B96: 114.23 | C96: 0.402 | D96: 6.1 | E96: 0.00053401 | F96: 0.0691 | G96: 0.0278 | H96: 0.521 | I96: 59.5 | J96: 49.46 | O96: 6.85396 | P96: 1315.08 | Q96: 217.53 | T96: 0.4439118 | U96: 1.1097794 | V96: =AVERAGE(T96:U96) -> 0.7768456
A97: 1,2,4-Trimethylbenzene (surrogate for C9 cpds) | B97: 120.19 | C97: 0.028 | D97: 42.1 | E97: 0.003502787 | F97: 0.453 | G97: 0.0127 | H97: 0.238 | I97: 28.6 | J97: 23.79 | O97: 7.04383 | P97: 1573.267 | Q97: 208.564 | T97: 0.2134675 | U97: 0.5336687 | V97: =AVERAGE(T97:U97) -> 0.3735681
A98: Decane + (decane used as surrogate) | B98: 142.29 | C98: 0.023 | D98: 49.52 | E98: 0.003480287 | F98: 0.45 | G98: 0.0103 | H98: 0.194 | I98: 27.6 | J98: 22.92 | O98: 7.44 | P98: 1843.12 | Q98: 230.22 | T98: 0.2057207 | U98: 0.5143016 | V98: =AVERAGE(T98:U98) -> 0.36001115
D100: 100 | E100: 0.01 | F100: 1 | G100: 0.05 | H100: 1 | I100: 120.31 | J100: 100
G102: 0.0018 | J102: 2.72 | K102: HAP only %
A103: WO2004050804A1 - Kerosene composition - Google Patents
A104: EPCRA Section 313 Industry Guidance for Petroleum Terminals and Bulk Storage Facilities
B108: MW | C108: VP, pure component, psia | D108: Diesel, Liquid, wt% | E108: Diesel, Liquid, moles | F108: Diesel, Liquid, mole frac | G108: Diesel, Partial Pressure, Pi, psia | H108: Diesel, Vapor, mole frac | I108: Avg MW vapor = y(i)*MW(i) | J108: Diesel, Vapor, wt% | L108: T = | M108: 68 | N108: F | O108: A | P108: B | Q108: C | T108: Ships | U108: Barges
M109: 20 | N109: C | T109: ppm | U109: ppm
A110: Benzene | B110: 78.11 | C110: 1.454 | D110: 0.0008 | E110: 1.0242e-07 | F110: 1.38e-05 | G110: 2.01e-05 | H110: 6.36e-05 | I110: 0.00497 | J110: 0.01 | O110: 6.90565 | P110: 1211.033 | Q110: 220.79 | T110: 4.08e-05 | U110: 0.000102 | V110: =AVERAGE(T110:U110) -> 7.14e-05
A111: Biphenyl | B111: 154.21 | C111: 0 | D111: 0.1 | E111: 6.48476e-06 | F111: 0.000875 | G111: 3.17e-07 | H111: 1e-06 | I111: 0.000154 | J111: 0 | O111: 7.2454 | P111: 1998.72 | Q111: 202.74 | T111: 1.269e-06 | U111: 3.172e-06 | V111: =AVERAGE(T111:U111) -> 2.2205e-06
A112: Ethylbenzene | B112: 106.17 | C112: 0.137 | D112: 0.013 | E112: 1.22445e-06 | F112: 0.000165 | G112: 2.26e-05 | H112: 7.16e-05 | I112: 0.0076 | J112: 0.01 | O112: 6.95719 | P112: 1424.255 | Q112: 213.21 | T112: 6.242e-05 | U112: 0.0001561 | V112: =AVERAGE(T112:U112) -> 0.00010926
A113: n-Hexane | B113: 86.18 | C113: 2.347 | D113: 1 | E113: 0.000116036 | F113: 0.0157 | G113: 0.0367 | H113: 0.116 | I113: 10 | J113: 10.82 | O113: 6.87601 | P113: 1171.17 | Q113: 224.41 | T113: 0.0823297 | U113: 0.2058244 | V113: =AVERAGE(T113:U113) -> 0.14407705
A114: Naphthalene | B114: 128.17 | C114: 0.003 | D114: 0.55 | E114: 4.29118e-05 | F114: 0.00579 | G114: 2.02e-05 | H114: 6.4e-05 | I114: 0.0082 | J114: 0.01 | O114: 7.37 | P114: 1968.36 | Q114: 222.61 | T114: 6.737e-05 | U114: 0.0001684 | V114: =AVERAGE(T114:U114) -> 0.000117885
A115: Phenol | B115: 94.11 | C115: 0.004 | D115: 0.064 | E115: 6.80047e-06 | F115: 0.000917 | G115: 3.9e-06 | H115: 1.24e-05 | I115: 0.00116 | J115: 0 | O115: 7.1345 | P115: 1516.07 | Q115: 174.57 | T115: 9.553e-06 | U115: 2.388e-05 | V115: =AVERAGE(T115:U115) -> 1.67165e-05
A116: Styrene | B116: 104.15 | C116: 0.088 | D116: 0.032 | E116: 3.07249e-06 | F116: 0.000414 | G116: 3.64e-05 | H116: 0.000115 | I116: 0.012 | J116: 0.01 | O116: 6.9571 | P116: 1445.58 | Q116: 209.44 | T116: 9.844e-05 | U116: 0.0002461 | V116: =AVERAGE(T116:U116) -> 0.00017227
A117: Toluene | B117: 92.14 | C117: 0.422 | D117: 0.032 | E117: 3.47298e-06 | F117: 0.000469 | G117: 0.000198 | H117: 0.000626 | I117: 0.0577 | J117: 0.06 | O117: 6.95464 | P117: 1344.8 | Q117: 219.48 | T117: 0.0004739 | U117: 0.0011847 | V117: =AVERAGE(T117:U117) -> 0.0008293
A118: Xylene | B118: 106.14 | C118: 0.126 | D118: 0.029 | E118: 2.73224e-06 | F118: 0.000369 | G118: 4.64e-05 | H118: 0.000147 | I118: 0.0156 | J118: 0.02 | O118: 6.99052 | P118: 1453.43 | Q118: 215.31 | T118: 0.0001281 | U118: 0.0003203 | V118: =AVERAGE(T118:U118) -> 0.0002242
A119: 2-Methylpentane (surrogate for C6 cpds) | B119: 86.18 | C119: 3.316 | D119: 3.7 | E119: 0.000429334 | F119: 0.0579 | G119: 0.192 | H119: 0.608 | I119: 52.4 | J119: 56.55 | O119: 6.8391 | P119: 1135.41 | Q119: 226.57 | T119: 0.4303835 | U119: 1.0759588 | V119: =AVERAGE(T119:U119) -> 0.75317115
A120: 2-Methylhexane (surrogate for C7 cpds) | B120: 100.2 | C120: 1 | D120: 5 | E120: 0.000499 | F120: 0.0673 | G120: 0.0673 | H120: 0.213 | I120: 21.3 | J120: 23.03 | O120: 6.87318 | P120: 1236.023 | Q120: 219.55 | T120: 0.1752878 | U120: 0.4382194 | V120: =AVERAGE(T120:U120) -> 0.3067536
A121: 1,2,4-Trimethylbenzene (surrogate for C9 cpds) | B121: 120.19 | C121: 0.028 | D121: 1 | E121: 8.32016e-05 | F121: 0.0112 | G121: 0.000314 | H121: 0.000994 | I121: 0.119 | J121: 0.13 | O121: 7.04383 | P121: 1573.267 | Q121: 208.564 | T121: 0.0009816 | U121: 0.002454 | V121: =AVERAGE(T121:U121) -> 0.0017178
A122: C10 cpds+ (decane used as surrogate) | B122: 142.29 | C122: 0.023 | D122: 88.48 | E122: 0.00621823 | F122: 0.839 | G122: 0.0192 | H122: 0.0609 | I122: 8.66 | J122: 9.35 | O122: 7.44 | P122: 1843.12 | Q122: 230.22 | T122: 0.0711566 | U122: 0.1778915 | V122: =AVERAGE(T122:U122) -> 0.12452405
D124: 100 | E124: 0.01 | F124: 1 | G124: 0.32 | H124: 1 | I124: 92.63 | J124: 100
G126: 0.0371 | J126: 10.93 | K126: HAP only %
A128: EPCRA Section 313 Industry Guidance for Petroleum Terminals and Bulk Storage Facilities
A129: Setup of composition of diesel (mass %). | Download Scientific Diagram
B133: MW | C133: VP, pure component, psia | D133: Residual, Liquid, wt% | E133: Residual, Liquid, moles | F133: Residual, Liquid, mole frac | G133: Residual, Partial Pressure, Pi, psia | H133: Residual, Vapor, mole frac | I133: Avg MW vapor = y(i)*MW(i) | J133: Residual, Vapor, wt% | L133: T = | M133: 68 | N133: F | O133: A | P133: B | Q133: C | T133: Ships | U133: Barges
M134: 20 | N134: C | T134: ppm | U134: ppm
A135: Benzene | B135: 78.11 | C135: 1.454 | D135: 0.001 | E135: 1.28025e-07 | F135: 1.79e-05 | G135: 2.6e-05 | H135: 0.000239 | I135: 0.0187 | J135: 0.02 | O135: 6.90565 | P135: 1211.033 | Q135: 220.79 | T135: 8.595e-05 | U135: 0.0002149 | V135: =AVERAGE(T135:U135) -> 0.000150425
A136: Ethylbenzene | B136: 106.17 | C136: 0.137 | D136: 0.0022 | E136: 2.07215e-07 | F136: 2.9e-05 | G136: 3.97e-06 | H136: 3.64e-05 | I136: 0.00387 | J136: 0 | O136: 6.95719 | P136: 1424.255 | Q136: 213.21 | T136: 1.78e-05 | U136: 4.45e-05 | V136: =AVERAGE(T136:U136) -> 3.115e-05
...

Sheet 50000MP
A1: 50,000 Model Plant
C2: Crude Petroleum | D2: Gasoline | E2: Kerosene | F2: Distillate Fuel Oil | G2: Residual Fuel Oil | H2: Naphtha & Solvents | I2: Benzene & Toluene | J2: Alcohols | K2: Total | M2: Hours Loading
A3: Gallons Loaded (1000 gal/yr) | C3: 4120.2338 | D3: 10338.9 | E3: 200.4071 | F3: 12521.45 | G3: 12212.37 | H3: 458.3607 | I3: 940.1768 | J3: 7641.983 | K3: 48433.883 | M3: =K3*1000/42/5000 -> 230.63754
A4: Loading Loss (TPY) | B4: Ships | C4: =C3*'Loading Loss'!H20/2000 -> 1.9014645 | D4: =D3*'Loading Loss'!B24/2000 -> 9.30501 | E4: =E3*'Loading Loss'!H4/2000 -> 0.00061330084 | F4: =F3*'Loading Loss'!H5/2000 -> 0.033351821 | G4: =G3*'Loading Loss'!H6/2000 -> 0.022320121 | H4: =H3*'Loading Loss'!H3/2000 -> 1.4149831 | I4: =I3*(AVERAGE('Loading Loss'!H7:H8))/2000 -> 0.2176305 | J4: =J3*(AVERAGE('Loading Loss'!H9:H10))/2000 -> 0.53711162 | K4: =SUM(C4:J4) -> 13.432485
B5: Barges | C5: =C3*'Loading Loss'!H20/2000 -> 1.9014645 | D5: =D3*'Loading Loss'!C24/2000 -> 17.57613 | E5: ='Loading Loss'!I4*'50000MP'!E3/2000 -> 0.0015332526 | F5: =F3*'Loading Loss'!I5/2000 -> 0.083379522 | G5: =G3*'Loading Loss'!I6/2000 -> 0.055800334 | H5: =H3*'Loading Loss'!I3/2000 -> 3.5374578 | I5: =I3*(AVERAGE('Loading Loss'!I7:I8))/2000 -> 0.54407626 | J5: =J3*(AVERAGE('Loading Loss'!I9:I10))/2000 -> 1.342779 | K5: =SUM(C5:J5) -> 25.042621 | M5: lb VOC emitted /hr
B6: Model Plant | C6: =AVERAGE(C4:C5) -> 1.9014645 | D6: =AVERAGE(D4:D5) -> 13.44057 | E6: =AVERAGE(E4:E5) -> 0.0010732767 | F6: =AVERAGE(F4:F5) -> 0.058365671 | G6: =AVERAGE(G4:G5) -> 0.039060227 | H6: =AVERAGE(H4:H5) -> 2.4762205 | I6: =AVERAGE(I4:I5) -> 0.38085338 | J6: =AVERAGE(J4:J5) -> 0.93994533 | K6: =SUM(C6:J6) -> 19.237553 | M6: =K6*2000/2400 -> 16.031294
A7: Percent of Total Loading Loss | C7: =C6/$K$6 -> 0.09884129 | D7: =D6/$K$6 -> 0.69866319 | E7: =E6/$K$6 -> 5.5790709e-05 | F7: =F6/$K$6 -> 0.0030339447 | G7: =G6/$K$6 -> 0.0020304156 | H7: =H6/$K$6 -> 0.12871806 | I7: =I6/$K$6 -> 0.019797392 | J7: =J6/$K$6 -> 0.048859922 | K7: =SUM(C7:J7) -> 1
A9: 50,000 Model Plant Emissions
B10: Benzene (TPY) | C10: Biphenyl (TPY) | D10: Chlorine (TPY) | E10: Cumene (TPY) | F10: Ethylbenzene (TPY) | G10: Ethylene Glycol (TPY) | H10: Hexane (TPY) | I10: Methanol (TPY) | J10: Napthalene (TPY) | K10: Phenol (TPY) | L10: Toluene (TPY) | M10: 2,2,4-Trimethyl-pentane (isooctane) (TPY) | N10: Styrene (TPY) | O10: Xylene (TPY) | P10: Total HAP (TPY)
A11: Ships | B11: =(C4*'Fuel Composition'!$J$32/100)+(D4*'Fuel Composition'!$J$6/100)+(E4*'Fuel Composition'!$J$87/100)+(F4*'Fuel Composition'!$J$110/100)+(G4*'Fuel Composition'!$J$135/100)+(H4*'Fuel Composition'!$J$64/100)+(I4*('Loading Loss'!H7/('Loading Loss'!H7+'Loading Loss'!H8))) -> 0.25459136 | C11: =(C4*'Fuel Composition'!$J$33/100)+(E4*'Fuel Composition'!$J$88/100)+(F4*'Fuel Composition'!$J$111/100) -> 1.9075976e-06 | D11: =G4*'Fuel Composition'!$J$137/100 -> 0.0038323648 | E11: =D4*'Fuel Composition'!$J$12/100 -> 0.00039081042 | F11: =(D4*'Fuel Composition'!$J$10/100)+(C4*'Fuel Composition'!$J$35/100)+(E4*'Fuel Composition'!$J$89/100)+(F4*'Fuel Composition'!$J$112/100)+(G4*'Fuel Composition'!$J$136/100)+(H4*'Fuel Composition'!$J$74/100) -> 0.0081727665 | G11: =J4*('Loading Loss'!H10/('Loading Loss'!H10+'Loading Loss'!H9)) -> 0.0005715057 | H11: =(D4*'Fuel Composition'!$J$7/100)+(C4*'Fuel Composition'!$J$36/100)+(E4*'Fuel Composition'!$J$90/100)+(F4*'Fuel Composition'!$J$113/100)+(H4*'Fuel Composition'!$J$66/100) -> 0.22927005 | I11: =J4*('Loading Loss'!H9/('Loading Loss'!H9+'Loading Loss'!H10)) -> 0.53654011 | J11: =(D4*'Fuel Composition'!$J$13/100)+(C4*'Fuel Composition'!$J$37/100)+(E4*'Fuel Composition'!$J$91/100)+(F4*'Fuel Composition'!$J$114/100)+(G4*'Fuel Composition'!$J$138/100) -> 5.7772741e-05 | K11: =(C4*'Fuel Composition'!$J$39/100)+(E4*'Fuel Composition'!$J$92/100)+(F4*'Fuel Composition'!$J$115/100) -> 1.9443956e-05 | L11: =(D4*'Fuel Composition'!$J$8/100)+(C4*'Fuel Composition'!$J$40/100)+(E4*'Fuel Composition'!$J$93/100)+(F4*'Fuel Composition'!$J$117/100)+(G4*'Fuel Composition'!$J$139/100)+(H4*'Fuel Composition'!$J$68/100)+(I4*('Loading Loss'!H8/('Loading Loss'!H8+'Loading Loss'!H7))) -> 0.16285877 | M11: =D4*'Fuel Composition'!$J$11/100 -> 0.026054028 | N11: =F4*'Fuel Composition'!$J$116/100 -> 3.3351821e-06 | O11: =(C4*'Fuel Composition'!$J$42/100)+(D4*'Fuel Composition'!$J$9/100)+(E4*'Fuel Composition'!$J$94/100)+(F4*'Fuel Composition'!$J$118/100)+(G4*'Fuel Composition'!$J$140/100)+(H4*'Fuel Composition'!$J$69/100) -> 0.032270808 | P11: =SUM(B11:O11) -> 1.254635
A12: Barges | B12: =(C5*'Fuel Composition'!$J$32/100)+(D5*'Fuel Composition'!$J$6/100)+(E5*'Fuel Composition'!$J$87/100)+(F5*'Fuel Composition'!$J$110/100)+(G5*'Fuel Composition'!$J$135/100)+(H5*'Fuel Composition'!$J$64/100)+(I5*('Loading Loss'!I7/('Loading Loss'!I7+'Loading Loss'!I8))) -> 0.58157499 | C12: =(C5*'Fuel Composition'!$J$33/100)+(E5*'Fuel Composition'!$J$88/100)+(F5*'Fuel Composition'!$J$111/100) -> 1.9167971e-06 | D12: =G5*'Fuel Composition'!$J$137/100 -> 0.0095809173 | E12: =D5*'Fuel Composition'!$J$12/100 -> 0.00073819746 | F12: =(D5*'Fuel Composition'!$J$10/100)+(C5*'Fuel Composition'!$J$35/100)+(E5*'Fuel Composition'!$J$89/100)+(F5*'Fuel Composition'!$J$112/100)+(G5*'Fuel Composition'!$J$136/100)+(H5*'Fuel Composition'!$J$74/100) -> 0.015881 | G12: =J5*('Loading Loss'!I10/('Loading Loss'!I10+'Loading Loss'!I9)) -> 0.0014287834 | H12: =(D5*'Fuel Composition'!$J$7/100)+(C5*'Fuel Composition'!$J$36/100)+(E5*'Fuel Composition'!$J$90/100)+(F5*'Fuel Composition'!$J$113/100)+(H5*'Fuel Composition'!$J$66/100) -> 0.44497024 | I12: =J5*('Loading Loss'!I9/('Loading Loss'!I9+'Loading Loss'!I10)) -> 1.3413503 | J12: =(D5*'Fuel Composition'!$J$13/100)+(C5*'Fuel Composition'!$J$37/100)+(E5*'Fuel Composition'!$J$91/100)+(F5*'Fuel Composition'!$J$114/100)+(G5*'Fuel Composition'!$J$138/100) -> 0.00010459109 | K12: =(C5*'Fuel Composition'!$J$39/100)+(E5*'Fuel Composition'!$J$92/100)+(F5*'Fuel Composition'!$J$115/100) -> 2.0087922e-05 | L12: =(D5*'Fuel Composition'!$J$8/100)+(C5*'Fuel Composition'!$J$40/100)+(E5*'Fuel Composition'!$J$93/100)+(F5*'Fuel Composition'!$J$117/100)+(G5*'Fuel Composition'!$J$139/100)+(H5*'Fuel Composition'!$J$68/100)+(I5*('Loading Loss'!I8/('Loading Loss'!I8+'Loading Loss'!I7))) -> 0.34258924 | M12: =D5*'Fuel Composition'!$J$11/100 -> 0.049213164 | N12: =F5*'Fuel Composition'!$J$116/100 -> 8.3379522e-06 | O12: =(C5*'Fuel Composition'!$J$42/100)+(D5*'Fuel Composition'!$J$9/100)+(E5*'Fuel Composition'!$J$94/100)+(F5*'Fuel Composition'!$J$118/100)+(G5*'Fuel Composition'!$J$140/100)+(H5*'Fuel Composition'!$J$69/100) -> 0.060482219 | P12: =SUM(B12:O12) -> 2.8479439
A13: Model Plant | B13: =AVERAGE(B11:B12) -> 0.41808318 | C13: =AVERAGE(C11:C12) -> 1.9121973e-06 | D13: =AVERAGE(D11:D12) -> 0.006706641 | E13: =AVERAGE(E11:E12) -> 0.00056450394 | F13: =AVERAGE(F11:F12) -> 0.012026883 | G13: =AVERAGE(G11:G12) -> 0.0010001445 | H13: =AVERAGE(H11:H12) -> 0.33712014 | I13: =AVERAGE(I11:I12) -> 0.93894518 | ... O13: =AVERAGE(O11:O12) -> 0.046376514 | P13: =SUM(B13:O13) -> 2.0512895
A15: Ships | B15: =(C4*'Fuel Composition'!$J$32/100)+(D4*'Fuel Composition'!$J$6/100)+(E4*'Fuel Composition'!$J$87/100)+(H4*'Fuel Composition'!$J$64/100)+(I4*('Loading Loss'!H7/('Loading Loss'!H7+'Loading Loss'!H8))) -> 0.25458356 | C15: =(C4*'Fuel Composition'!$J$33/100)+(E4*'Fuel Composition'!$J$88/100) -> 1.9075976e-06 | D15: 0 | E15: =D4*'Fuel Composition'!$J$12/100 -> 0.00039081042 | F15: =(D4*'Fuel Composition'!$J$10/100)+(C4*'Fuel Composition'!$J$35/100)+(E4*'Fuel Composition'!$J$89/100)+(H4*'Fuel Composition'!$J$74/100) -> 0.0081694313 | G15: 0 | H15: =(D4*'Fuel Composition'!$J$7/100)+(C4*'Fuel Composition'!$J$36/100)+(E4*'Fuel Composition'!$J$90/100)+(H4*'Fuel Composition'!$J$66/100) -> 0.22566138 | I15: 0 | J15: =(D4*'Fuel Composition'!$J$13/100)+(C4*'Fuel Composition'!$J$37/100)+(E4*'Fuel Composition'!$J$91/100) -> 5.4437559e-05 | K15: =(C4*'Fuel Composition'!$J$39/100)+(E4*'Fuel Composition'!$J$92/100)+(F4*'Fuel Composition'!$J$115/100) -> 1.9443956e-05 | L15: =(D8*'Fuel Composition'!$J$8/100)+(C8*'Fuel Composition'!$J$40/100)+(E8*'Fuel Composition'!$J$93/100)+(F8*'Fuel Composition'!$J$117/100)+(G8*'Fuel Composition'!$J$139/100)+(H8*'Fuel Composition'!$J$68/100)+(I8*('Loading Loss'!H12/('Loading Loss'!H12+'Loading Loss'!H11))) -> #DIV/0! | M15: =D8*'Fuel Composition'!$J$11/100 -> 0 | N15: =F8*'Fuel Composition'!$J$116/100 -> 0 | O15: =(C8*'Fuel Composition'!$J$42/100)+(D8*'Fuel Composition'!$J$9/100)+(E8*'Fuel Composition'!$J$94/100)+(F8*'Fuel Composition'!$J$118/100)+(G8*'Fuel Composition'!$J$140/100)+(H8*'Fuel Composition'!$J$69/100) -> 0 | P15: =SUM(B15:O15) -> #DIV/0!
A16: Barges | B16: =(C5*'Fuel Composition'!$J$32/100)+(D5*'Fuel Composition'!$J$6/100)+(E5*'Fuel Composition'!$J$87/100)+(H5*'Fuel Composition'!$J$64/100)+(I9*('Loading Loss'!I7/('Loading Loss'!I7+'Loading Loss'!I8))) -> 0.17836909 | C16: =(C5*'Fuel Composition'!$J$33/100)+(E5*'Fuel Composition'!$J$88/100) -> 1.9167971e-06 | D16: 0 | E16: =D5*'Fuel Composition'!$J$12/100 -> 0.00073819746 | F16: =(D5*'Fuel Composition'!$J$10/100)+(C5*'Fuel Composition'!$J$35/100)+(E5*'Fuel Composition'!$J$89/100)+(H5*'Fuel Composition'!$J$74/100) -> 0.015872662 | G16: 0 | H16: =(D5*'Fuel Composition'!$J$7/100)+(C5*'Fuel Composition'!$J$36/100)+(E5*'Fuel Composition'!$J$90/100)+(H5*'Fuel Composition'!$J$66/100) -> 0.43594858 | I16: 0 | J16: =(D5*'Fuel Composition'!$J$13/100)+(C5*'Fuel Composition'!$J$37/100)+(E5*'Fuel Composition'!$J$91/100) -> 9.6253134e-05 | K16: =(C5*'Fuel Composition'!$J$39/100)+(E5*'Fuel Composition'!$J$92/100)+(F5*'Fuel Composition'!$J$115/100) -> 2.0087922e-05 | L16: =(D9*'Fuel Composition'!$J$8/100)+(C9*'Fuel Composition'!$J$40/100)+(E9*'Fuel Composition'!$J$93/100)+(F9*'Fuel Composition'!$J$117/100)+(G9*'Fuel Composition'!$J$139/100)+(H9*'Fuel Composition'!$J$68/100)+(I9*('Loading Loss'!I12/('Loading Loss'!I12+'Loading Loss'!I11))) -> #DIV/0! | M16: =D9*'Fuel Composition'!$J$11/100 -> 0 | N16: =F9*'Fuel Composition'!$J$116/100 -> 0 | O16: =(C9*'Fuel Composition'!$J$42/100)+(D9*'Fuel Composition'!$J$9/100)+(E9*'Fuel Composition'!$J$94/100)+(F9*'Fuel Composition'!$J$118/100)+(G9*'Fuel Composition'!$J$140/100)+(H9*'Fuel Composition'!$J$69/100) -> 0 | P16: =SUM(B16:O16) -> #DIV/0!
A17: Model Plant | B17: =AVERAGE(B15:B16) -> 0.21647632 | C17: =AVERAGE(C15:C16) -> 1.9121973e-06 | D17: 0 | E17: =AVERAGE(E15:E16) -> 0.00056450394 | F17: =AVERAGE(F15:F16) -> 0.012021047 | G17: =AVERAGE(G15:G16) -> 0 | H17: =AVERAGE(H15:H16) -> 0.33080498 | I17: =AVERAGE(I15:I16) -> 0 | J17: =AVERAGE(J15:J16) -> 7.5345347e-05 | K17: =AVERAGE(K15:K16) -> 1.9765939e-05 | L17: =AVERAGE(L15:L16) -> #DIV/0! | ... O17: =AVERAGE(O15:O16) -> 0 | P17: =SUM(B17:O17) -> #DIV/0!
B24: Carbon Adsorber | I24: Recuperative Oxidizer
B25: Costs (2021 dollars) | F25: Cost Effectiveness ($/ton) | I25: Costs (2021 dollars) | L25: Cost Effectiveness ($/ton)
B26: Capital (TCI) | C26: Annual Costs | D26: Solvent Recovery Credit | E26: Total Annual Cost (TAC) | I26: Capital (TCI) | J26: Annual Costs | K26: Total Annual Cost (TAC)
A27: Typical MTVLO Facility | H27: Typical MTVLO Facility | P27: Average Loading Loss
A28: 240 hrs (no exemption) | B28: 2064594 | C28: =57779+268364 -> 326143 | D28: 30054 | E28: 296090 | F28: =E28/P13 -> 144343.35 | H28: 240 hrs (no exemption) | I28: 946003 | J28: =13347+117770 -> 131117 | K28: 131117 | L28: =K28/P13 -> 63919.306 | P28: lb/hr
A29: 72 hrs (1.5 psia) | B29: 2064594 | C29: =52246+267784 -> 320030 | D29: 9016 | E29: 311014 | H29: 72 hrs (1.5 psia) | I29: 946003 | J29: =4004+117232 -> 121236 | K29: 121236 | O29: Naptha and Solvents | P29: 1286.2715 | Q29: 0.11521589 | R29: =Q29*P29 -> 148.19891
A30: 78 hrs (1 or 0.5 psia) | B30: 2064594 | C30: =52444+267805 -> 320249 | D30: 9767 | E30: 310481 | H30: 78 hrs (1 or 0.5 psia) | I30: 946003 | J30: =4338+117251 -> 121589 | K30: 121589 | O30: Kerosene | P30: 1.2751151 | Q30: 4.9938416e-05 | R30: =Q30*P30 -> 6.3677229e-05
O31: Distillate Oil No. 2 | P31: 1.1098224 | Q31: 0.0027156922 | R31: =Q31*P31 -> 0.0030139361
A32: Assumptions: | O32: Residual Oil No. 6 | P32: 0.76152709 | Q32: 0.0018174305 | R32: =Q32*P32 -> 0.0013840226
A33: 1. Loading Rate = 5000 bbl/hr | O33: Benzene | P33: 142.94702 | Q33: =I7/2 -> 0.0098986961 | R33: =Q33*P33 -> 1.4149891
A34: 2. Ships and Barges are loaded equally | O34: Toluene | P34: 49.951544 | Q34: =Q33 -> 0.0098986961 | R34: =Q34*P34 -> 0.49445515
A35: 3. Up to 1 vessel can be loaded at once | O35: Methanol | P35: 58.507949 | Q35: =J7/2 -> 0.024429961 | R35: =Q35*P35 -> 1.4293469
O36: Ethylene glycol | P36: 0.06232125 | Q36: =Q35 -> 0.024429961 | R36: =Q36*P36 -> 0.0015225057
O37: Crude Oil | P37: 240.15728 | Q37: 0.19337038 | R37: =Q37*P37 -> 46.439305
O38: Gasoline | P38: 309.52381 | Q38: 0.62537532 | R38: =Q38*P38 -> 193.56855
Q39: =SUM(Q29:Q38) -> 1.007202 | R39: =SUM(R29:R38) -> 391.55154 | S39: VOC Emission Rate lb/hr

Sheet 25000000MP
A1: 25,000,000 Model Plant
C2: Crude Petroleum | D2: Gasoline | E2: Kerosene | F2: Distillate Fuel Oil | G2: Residual Fuel Oil | H2: Naphtha & Solvents | I2: Benzene & Toluene | J2: Alcohols | K2: Total | M2: Hours Loading
A3: Gallons Loaded (1000 gal/yr) | C3: 11575663 | D3: 4344659 | E3: 430616.7 | F3: 3936982 | G3: 663764.7 | H3: 1525854 | I3: 144434.7 | J3: 642589.7 | K3: =SUM(C3:J3) -> 23264564 | M3: =K3*1000/42/7500 -> 73855.759 | N3: =M3/8760 -> 8.4310227
A4: Loading Loss (TPY) | B4: Ships | C4: =C3*'Loading Loss'!H20/2000 -> 5342.103 | D4: =D3*'Loading Loss'!B24/2000 -> 3910.1931 | E4: =E3*'Loading Loss'!H4/2000 -> 1.3178055 | F4: =F3*'Loading Loss'!H5/2000 -> 10.486447 | G4: =G3*'Loading Loss'!H6/2000 -> 1.2131395 | H4: =H3*'Loading Loss'!H3/2000 -> 4710.39 | I4: =I3*(AVERAGE('Loading Loss'!H7:H8))/2000 -> 33.433495 | J4: =J3*(AVERAGE('Loading Loss'!H9:H10))/2000 -> 45.163983 | K4: =SUM(C4:J4) -> 14054.301
B5: Barges | C5: =C3*'Loading Loss'!H20/2000 -> 5342.103 | D5: =D3*'Loading Loss'!C24/2000 -> 7385.9203 | E5: ='Loading Loss'!I4*'25000000MP'!E3/2000 -> 3.2945149 | F5: =F3*'Loading Loss'!I5/2000 -> 26.216107 | G5: =G3*'Loading Loss'!I6/2000 -> 3.0328504 | H5: =H3*'Loading Loss'!I3/2000 -> 11775.975 | I5: =I3*(AVERAGE('Loading Loss'!I7:I8))/2000 -> 83.583738 | J5: =J3*(AVERAGE('Loading Loss'!I9:I10))/2000 -> 112.90996 | K5: =SUM(C5:J5) -> 24733.036 | M5: lb VOC emitted /hr
B6: Model Plant | C6: =AVERAGE(C4:C5) -> 5342.103 | D6: =AVERAGE(D4:D5) -> 5648.0567 | E6: =AVERAGE(E4:E5) -> 2.3061602 | F6: =AVERAGE(F4:F5) -> 18.351277 | G6: =AVERAGE(G4:G5) -> 2.122995 | H6: =AVERAGE(H4:H5) -> 8243.1826 | I6: =AVERAGE(I4:I5) -> 58.508616 | J6: =AVERAGE(J4:J5) -> 79.036971 | K6: =SUM(C6:J6) -> 19393.668 | M6: =K6*2000/8760 -> 4427.7782
A7: Percent of Total Loading Loss | C7: =C6/$K$6 -> 0.27545604 | D7: =D6/$K$6 -> 0.29123199 | E7: =E6/$K$6 -> 0.00011891305 | F7: =F6/$K$6 -> 0.00094625095 | G7: =G6/$K$6 -> 0.00010946846 | H7: =H6/$K$6 -> 0.42504504 | I7: =I6/$K$6 -> 0.0030168927 | J7: =J6/$K$6 -> 0.0040754008 | K7: =SUM(C7:J7) -> 1
A9: 25,000,000 Model Plant Emissions
B10: Benzene (TPY) | C10: Biphenyl (TPY) | D10: Chlorine (TPY) | E10: Cumene (TPY) | F10: Ethylbenzene (TPY) | G10: Ethylene Glycol (TPY) | H10: Hexane (TPY) | I10: Methanol (TPY) | J10: Napthalene (TPY) | K10: Phenol (TPY) | L10: Toluene (TPY) | M10: 2,2,4-Trimethyl-pentane (isooctane) (TPY) | N10: Styrene (TPY) | O10: Xylene (TPY) | P10: Total HAP (TPY)
A11: Ships | B11: =(C4*'Fuel Composition'!$J$32/100)+(D4*'Fuel Composition'!$J$6/100)+(E4*'Fuel Composition'!$J$87/100)+(F4*'Fuel Composition'!$J$110/100)+(G4*'Fuel Composition'!$J$135/100)+(H4*'Fuel Composition'!$J$64/100)+(I4*('Loading Loss'!H9/('Loading Loss'!H9+'Loading Loss'!H10))) -> 124.23375 | C11: =(C4*'Fuel Composition'!$J$33/100)+(E4*'Fuel Composition'!$J$88/100)+(F4*'Fuel Composition'!$J$111/100) -> 0.0053552811 | D11: =G4*'Fuel Composition'!$J$137/100 -> 0.20829605 | E11: =D4*'Fuel Composition'!$J$12/100 -> 0.16422811 | F11: =(D4*'Fuel Composition'!$J$10/100)+(C4*'Fuel Composition'!$J$35/100)+(E4*'Fuel Composition'!$J$89/100)+(F4*'Fuel Composition'!$J$112/100)+(G4*'Fuel Composition'!$J$136/100)+(H4*'Fuel Composition'!$J$74/100) -> 8.0505678 | G11: =J4*('Loading Loss'!H10/('Loading Loss'!H10+'Loading Loss'!H9)) -> 0.048056071 | H11: =(D4*'Fuel Composition'!$J$7/100)+(C4*'Fuel Composition'!$J$36/100)+(E4*'Fuel Composition'!$J$90/100)+(F4*'Fuel Composition'!$J$113/100)+(H4*'Fuel Composition'!$J$66/100) -> 507.17581 | I11: =J4*('Loading Loss'!H9/('Loading Loss'!H9+'Loading Loss'!H10)) -> 45.115927 | J11: =(D4*'Fuel Composition'!$J$13/100)+(C4*'Fuel Composition'!$J$37/100)+(E4*'Fuel Composition'!$J$91/100)+(F4*'Fuel Composition'!$J$114/100)+(G4*'Fuel Composition'!$J$138/100) -> 0.042626925 | K11: =(C4*'Fuel Composition'!$J$39/100)+(E4*'Fuel Composition'!$J$92/100)+(F4*'Fuel Composition'!$J$115/100) -> 0.054343494 | L11: =(D4*'Fuel Composition'!$J$8/100)+(C4*'Fuel Composition'!$J$40/100)+(E4*'Fuel Composition'!$J$93/100)+(F4*'Fuel Composition'!$J$117/100)+(G4*'Fuel Composition'!$J$139/100)+(H4*'Fuel Composition'!$J$68/100)+(I4*('Loading Loss'!H8/('Loading Loss'!H8+'Loading Loss'!H7))) -> 79.749648 | M11: =D4*'Fuel Composition'!$J$11/100 -> 10.948541 | N11: =F4*'Fuel Composition'!$J$116/100 -> 0.0010486447 | O11: =(C4*'Fuel Composition'!$J$42/100)+(D4*'Fuel Composition'!$J$9/100)+(E4*'Fuel Composition'!$J$94/100)+(F4*'Fuel Composition'!$J$118/100)+(G4*'Fuel Composition'!$J$140/100)+(H4*'Fuel Composition'!$J$69/100) -> 22.59471 | P11: =SUM(B11:O11) -> 798.39291
A12: Barges | B12: =(C5*'Fuel Composition'!$J$32/100)+(D5*'Fuel Composition'!$J$6/100)+(E5*'Fuel Composition'!$J$87/100)+(F5*'Fuel Composition'!$J$110/100)+(G5*'Fuel Composition'!$J$135/100)+(H5*'Fuel Composition'!$J$64/100)+(I5*('Loading Loss'!I9/('Loading Loss'!I9+'Loading Loss'!I10))) -> 265.02446 | C12: =(C5*'Fuel Composition'!$J$33/100)+(E5*'Fuel Composition'!$J$88/100)+(F5*'Fuel Composition'!$J$111/100) -> 0.0053750482 | D12: =G5*'Fuel Composition'!$J$137/100 -> 0.52074042 | E12: =D5*'Fuel Composition'!$J$12/100 -> 0.31020865 | F12: =(D5*'Fuel Composition'!$J$10/100)+(C5*'Fuel Composition'!$J$35/100)+(E5*'Fuel Composition'!$J$89/100)+(F5*'Fuel Composition'!$J$112/100)+(G5*'Fuel Composition'!$J$136/100)+(H5*'Fuel Composition'!$J$74/100) -> 16.851095 | G12: =J5*('Loading Loss'!I10/('Loading Loss'!I10+'Loading Loss'!I9)) -> 0.12014178 | H12: =(D5*'Fuel Composition'!$J$7/100)+(C5*'Fuel Composition'!$J$36/100)+(E5*'Fuel Composition'!$J$90/100)+(F5*'Fuel Composition'!$J$113/100)+(H5*'Fuel Composition'!$J$66/100) -> 1016.4415 | I12: =J5*('Loading Loss'!I9/('Loading Loss'!I10+'Loading Loss'!I9)) -> 112.78982 | J12: =(D5*'Fuel Composition'!$J$13/100)+(C5*'Fuel Composition'!$J$37/100)+(E5*'Fuel Composition'!$J$91/100)+(F5*'Fuel Composition'!$J$114/100)+(G5*'Fuel Composition'!$J$138/100) -> 0.062566882 | K12: =(C5*'Fuel Composition'!$J$39/100)+(E5*'Fuel Composition'!$J$92/100)+(F5*'Fuel Composition'!$J$115/100) -> 0.055727191 | L12: =(D5*'Fuel Composition'!$J$8/100)+(C5*'Fuel Composition'!$J$40/100)+(E5*'Fuel Composition'!$J$93/100)+(F5*'Fuel Composition'!$J$117/100)+(G5*'Fuel Composition'!$J$139/100)+(H5*'Fuel Composition'!$J$68/100)+(I5*('Loading Loss'!I8/('Loading Loss'!I8+'Loading Loss'!I7))) -> 159.29768 | M12: =D5*'Fuel Composition'!$J$11/100 -> 20.680577 | N12: =F5*'Fuel Composition'!$J$116/100 -> 0.0026216107 | O12: =(C5*'Fuel Composition'!$J$42/100)+(D5*'Fuel Composition'!$J$9/100)+(E5*'Fuel Composition'!$J$94/100)+(F5*'Fuel Composition'!$J$118/100)+(G5*'Fuel Composition'!$J$140/100)+(H5*'Fuel Composition'!$J$69/100) -> 41.867292 | P12: =SUM(B12:O12) -> 1634.0298
A13: Model Plant | B13: =AVERAGE(B11:B12) -> 194.62911 | C13: =AVERAGE(C11:C12) -> 0.0053651646 | D13: =AVERAGE(D11:D12) -> 0.36451824 | E13: =AVERAGE(E11:E12) -> 0.23721838 | F13: =AVERAGE(F11:F12) -> 12.450831 | G13: =AVERAGE(G11:G12) -> 0.084098927 | H13: =AVERAGE(H11:H12) -> 761.80868 | I13: =AVERAGE(I11:I12) -> 78.952872 | ... O13: =AVERAGE(O11:O12) -> 32.231001 | P13: =SUM(B13:O13) -> 1216.2114
B21: Carbon Adsorber | I21: Recuperative Oxidizer
B22: Costs (2021 dollars) | F22: Cost Effectiveness ($/ton) | I22: Costs (2021 dollars) | L22: Cost Effectiveness ($/ton)
B23: Capital (TCI) | C23: Annual Costs | D23: Solvent Recovery Credit | E23: Total Annual Cost (TAC) | I23: Capital (TCI) | J23: Annual Costs | K23: Total Annual Cost (TAC)
A24: Typical MTVLO Facility | H24: Typical MTVLO Facility | O24: Average Loading Loss
A25: 8760 hrs/yr | B25: 3456350 | C25: =172141+458537 -> 630678 | D25: 392413 | E25: 238266 | F25: =E25/(P13*0.97) -> 201.9674 | H25: 8760 hrs/yr | I25: 1163987 | J25: =278778+172016 -> 450794 | K25: 450793 | L25: =K25/(P13*0.97) -> 382.11701 | O25: lb/hr
N29: Naptha and Solvents | O29: 1286.2715 | P29: =H7 -> 0.42504504 | Q29: =P29*O29 -> 546.72332
N30: Kerosene | O30: 1.2751151 | P30: =E7 -> 0.00011891305 | Q30: =P30*O30 -> 0.00015162783
A31: Assumptions: | N31: Distillate Oil No. 2 | O31: 1.1098224 | P31: =F7 -> 0.00094625095 | Q31: =P31*O31 -> 0.0010501705
A32: 1. Loading Rate = 7500 bbl/hr | N32: Residual Oil No. 6 | O32: 0.76152709 | P32: =G7 -> 0.00010946846 | Q32: =P32*O32 -> 8.3363197e-05
A33: 2. Ships and Barges are loaded equally | N33: Benzene | O33: 142.94702 | P33: =I7/2 -> 0.0015084463 | Q33: =P33*O33 -> 0.21562791
A34: 3. Up to 9 vessels can be loaded at once | N34: Toluene | O34: 49.951544 | P34: =P33 -> 0.0015084463 | Q34: =P34*O34 -> 0.075349224
N35: Methanol | O35: 58.507949 | P35: =J7/2 -> 0.0020377004 | Q35: =P35*O35 -> 0.11922167
N36: Ethylene glycol | O36: 0.06232125 | P36: =P35 -> 0.0020377004 | Q36: =P36*O36 -> 0.00012699204
N37: Crude Oil | O37: 240.15728 | P37: =C7 -> 0.27545604 | Q37: =P37*O37 -> 66.152773
N38: Gasoline | O38: 309.52381 | P38: =D7 -> 0.29123199 | Q38: =P38*O38 -> 90.143236
P39: =SUM(P29:P38) -> 1 | Q39: =SUM(Q29:Q38) -> 703.43094 | R39: VOC Emission Rate lb/hr

Sheet Assumptions
A1: Assumptions
A2: Loading Scenario | B2: 100000 | C2: 500000 | D2: 5000000
A3: Total Loading Rate (all compartments, bbl/hr) | B3: 5000 | C3: 5000 | D3: 5000
A4: Vessels loaded simultaneously | B4: 1 | C4: 1 | D4: 2
A6: Carbon Adsorber
A7: Loading Scenario | B7: 100000 | C7: 500000 | D7: 5000000
A8: Dollar Year | B8: 2023 | C8: 2023 | D8: 2023
A9: Interest Rate (%) | B9: 7.5 | C9: 7.5 | D9: 7.5
A10: Pollutant Controlled | B10: Benzene | C10: Benzene | D10: Benzene
A11: Operating Hours (No VP Limit) | B11: 520 | C11: 2400 | D11: 8760
A12: Operating hours (>1.5 psia only) | B12: 110 | C12: 1080 | D12: 8760
A13: VOC Emission Rate (lb/hr) | B13: 546 | C13: 546 | D13: 1092
A14: Control Efficiency (%) | B14: 97 | C14: 97 | D14: 97
A15: Solvent Recovery Credit ($/ton) | B15: 672 | C15: 672 | D15: 672
A18: Thermal Oxidizer
A19: Loading Scenario | B19: 100000 | C19: 500000 | D19: 5000000
A20: Dollar Year | B20: 2021 | C20: 2021 | D20: 2021
A21: Interest Rate (%) | B21: 5.5 | C21: 5.5 | D21: 5.5
A22: Operating Hours (No VP Limit) | B22: 520 | C22: 2400 | D22: 8760
A23: Operating hours (>1.5 psia only) | B23: 110 | C23: 1080 | D23: 8760
A24: VOC Composition based on | B24: Gasoline | C24: Gasoline | D24: Gasoline
A25: Heat Recovery (%) | B25: 0 | C25: 0 | D25: 0
A26: Natural Gas Cost ($/scf) | B26: 0.00351 | C26: 0.00351 | D26: 0.00351
A27: Electricity Cost ($/kWh) | B27: 0.0641 | C27: 0.0641 | D27: 0.0641

Sheet Sheet1
B1: Gasoline | C1: Crude Oil | D1: Naphtha | E1: Kerosene | F1: Distallate | G1: Residual | H1: Benzene | I1: Toluene | J1: Methanol | K1: Ethylene Glycol | N1: 50000 | O1: 500000 | P1: 5000000 | Q1: 25000000
A2: Benzene | B2: 3.31 | C2: 0.9110661 | D2: 17.33829 | E2: 0.00184425 | F2: 7.14e-05 | G2: 0.000150425 | H2: 1.647126 | N2: =($B2*$D$38)+($C$38*$C2)+($H$38*$D2)+($E$38*$E2)+($F2*$F$38)+($G2*$G$38)+($H2*$I$38/2)+($I2*$I$38/2)+($J2*$J$38/2)+($K2*$J$38/2) -> 4.2584067 | O2: =($B2*$D$39)+($C$39*$C2)+($H$39*$D2)+($E$39*$E2)+($F2*$F$39)+($G2*$G$39)+($H2*$I$39/2)+($I2*$I$39/2)+($J2*$J$39/2)+($K2*$J$39/2) -> 7.591573 | P2: =($B2*$D$40)+($C$40*$C2)+($H$40*$D2)+($E$40*$E2)+($F2*$F$40)+($G2*$G$40)+($H2*$I$40/2)+($I2*$I$40/2)+($J2*$J$40/2)+($K2*$J$40/2) -> 8.6407319 | Q2: =($B2*$D$41)+($C$41*$C2)+($H$41*$D2)+($E$41*$E2)+($F2*$F$41)+($G2*$G$41)+($H2*$I$41/2)+($I2*$I$41/2)+($J2*$J$41/2)+($K2*$J$41/2) -> 6.6972544
A3: Biphenyl | C3: 0.0003049 | E3: 1.3763e-05 | F3: 2.2205e-06 | N3: =(B3*$D$38)+($C$38*C3)+($H$38*D3)+($E$38*E3)+(F3*$F$38)+(G3*$G$38)+(H3*$I$38/2)+(I3*$I$38/2)+(J3*$J$38/2)+(K3*$J$38/2) -> 5.8965347e-05 | O3: =($B3*$D$39)+($C$39*$C3)+($H$39*$D3)+($E$39*$E3)+($F3*$F$39)+($G3*$G$39)+($H3*$I$39/2)+($I3*$I$39/2)+($J3*$J$39/2)+($K3*$J$39/2) -> 7.5987794e-05 | P3: =($B3*$D$40)+($C$40*$C3)+($H$40*$D3)+($E$40*$E3)+($F3*$F$40)+($G3*$G$40)+($H3*$I$40/2)+($I3*$I$40/2)+($J3*$J$40/2)+($K3*$J$40/2) -> 9.4405993e-06 | Q3: =($B3*$D$41)+($C$41*$C3)+($H$41*$D3)+($E$41*$E3)+($F3*$F$41)+($G3*$G$41)+($H3*$I$41/2)+($I3*$I$41/2)+($J3*$J$41/2)+($K3*$J$41/2) -> 0.00013837574
A4: Hexane | B4: 3.32 | C4: 8.1213815 | D4: 132.16095 | E4: 0.0037212 | F4: 0.14407705 | N4: =(B4*$D$38)+($C$38*C4)+($H$38*D4)+($E$38*E4)+(F4*$F$38)+(G4*$G$38)+(H4*$I$38/2)+(I4*$I$38/2)+(J4*$J$38/2)+(K4*$J$38/2) -> 18.874113 | O4: =($B4*$D$39)+($C$39*$C4)+($H$39*$D4)+($E$39*$E4)+($F4*$F$39)+($G4*$G$39)+($H4*$I$39/2)+($I4*$I$39/2)+($J4*$J$39/2)+($K4*$J$39/2) -> 50.306185 | P4: =($B4*$D$40)+($C$40*$C4)+($H$40*$D4)+($E$40*$E4)+($F4*$F$40)+($G4*$G$40)+($H4*$I$40/2)+($I4*$I$40/2)+($J4*$J$40/2)+($K4*$J$40/2) -> 53.496403 | Q4: =($B4*$D$41)+($C$41*$C4)+($H$41*$D4)+($E$41*$E4)+($F4*$F$41)+($G4*$G$41)+($H4*$I$41/2)+($I4*$I$41/2)+($J4*$J$41/2)+($K4*$J$41/2) -> 46.759558
A5: Toluene | B5: 4.305 | C5: 0.5207329 | D5: 8.389971 | E5: 0.01740235 | F5: 0.0008293 | G5: 0.000262 | I5: 0.582768 | N5: =(B5*$D$38)+($C$38*C5)+($H$38*D5)+($E$38*E5)+(F5*$F$38)+(G5*$G$38)+(H5*$I$38/2)+(I5*$I$38/2)+(J5*$J$38/2)+(K5*$J$38/2) -> 3.7647601 | O5: =($B5*$D$39)+($C$39*$C5)+($H$39*$D5)+($E$39*$E5)+($F5*$F$39)+($G5*$G$39)+($H5*$I$39/2)+($I5*$I$39/2)+($J5*$J$39/2)+($K5*$J$39/2) -> 4.6578525 | P5: =($B5*$D$40)+($C$40*$C5)+($H$40*$D5)+($E$40*$E5)+($F5*$F$40)+($G5*$G$40)+($H5*$I$40/2)+($I5*$I$40/2)+($J5*$J$40/2)+($K5*$J$40/2) -> 5.7072743 | Q5: =($B5*$D$41)+($C$41*$C5)+($H$41*$D5)+($E$41*$E5)+($F5*$F$41)+($G5*$G$41)+($H5*$I$41/2)+($I5*$I$41/2)+($J5*$J$41/2)+($K5*$J$41/2) -> 3.8702618
A6: Xylene | B6: 1.275 | C6: 0.251263 | D6: 2.336237 | E6: 0.0123807 | F6: 0.0002242 | G6: 0.000169395 | N6: =(B6*$D$38)+($C$38*C6)+($H$38*D6)+($E$38*E6)+(F6*$F$38)+(G6*$G$38)+(H6*$I$38/2)+(I6*$I$38/2)+(J6*$J$38/2)+(K6*$J$38/2) -> 1.1151135 | O6: =($B6*$D$39)+($C$39*$C6)+($H$39*$D6)+($E$39*$E6)+($F6*$F$39)+($G6*$G$39)+($H6*$I$39/2)+($I6*$I$39/2)+($J6*$J$39/2)+($K6*$J$39/2) -> 1.3502785 | P6: =($B6*$D$40)+($C$40*$C6)+($H$40*$D6)+($E$40*$E6)+($F6*$F$40)+($G6*$G$40)+($H6*$I$40/2)+($I6*$I$40/2)+($J6*$J$40/2)+($K6*$J$40/2) -> 1.6348803 | Q6: =($B6*$D$41)+($C$41*$C6)+($H$41*$D6)+($E$41*$E6)+($F6*$F$41)+($G6*$G$41)+($H6*$I$41/2)+($I6*$I$41/2)+($J6*$J$41/2)+($K6*$J$41/2) -> 1.1424772
A7: Ethylbenzene | B7: 0.315 | C7: 0.0665378 | D7: 1.8135994 | E7: 0.00551235 | F7: 0.00010926 | G7: 3.115e-05 | N7: =(B7*$D$38)+($C$38*C7)+($H$38*D7)+($E$38*E7)+(F7*$F$38)+(G7*$G$38)+(H7*$I$38/2)+(I7*$I$38/2)+(J7*$J$38/2)+(K7*$J$38/2) -> 0.41881576 | O7: =($B7*$D$39)+($C$39*$C7)+($H$39*$D7)+($E$39*$E7)+($F7*$F$39)+($G7*$G$39)+($H7*$I$39/2)+($I7*$I$39/2)+($J7*$J$39/2)+($K7*$J$39/2) -> 0.77531845 | P7: =($B7*$D$40)+($C$40*$C7)+($H$40*$D7)+($E$40*$E7)+($F7*$F$40)+($G7*$G$40)+($H7*$I$40/2)+($I7*$I$40/2)+($J7*$J$40/2)+($K7*$J$40/2) -> 0.88466301 | Q7: =($B7*$D$41)+($C$41*$C7)+($H$41*$D7)+($E$41*$E7)+($F7*$F$41)+($G7*$G$41)+($H7*$I$41/2)+($I7*$I$41/2)+($J7*$J$41/2)+($K7*$J$41/2) -> 0.68043481
A8: 2,2,4-Trimethylpentane (isooctane) | B8: 1.16 | N8: =(B8*$D$38)+($C$38*C8)+($H$38*D8)+($E$38*E8)+(F8*$F$38)+(G8*$G$38)+(H8*$I$38/2)+(I8*$I$38/2)+(J8*$J$38/2)+(K8*$J$38/2) -> 0.72543537 | O8: =($B8*$D$39)+($C$39*$C8)+($H$39*$D8)+($E$39*$E8)+($F8*$F$39)+($G8*$G$39)+($H8*$I$39/2)+($I8*$I$39/2)+($J8*$J$39/2)+($K8*$J$39/2) -> 0.41406907 | P8: =($B8*$D$40)+($C$40*$C8)+($H$40*$D8)+($E$40*$E8)+($F8*$F$40)+($G8*$G$40)+($H8*$I$40/2)+($I8*$I$40/2)+($J8*$J$40/2)+($K8*$J$40/2) -> 0.65412358 | Q8: =($B8*$D$41)+($C$41*$C8)+($H$41*$D8)+($E$41*$E8)+($F8*$F$41)+($G8*$G$41)+($H8*$I$41/2)+($I8*$I$41/2)+($J8*$J$41/2)+($K8*$J$41/2) -> 0.25465944
A9: Phenol | C9: 0.001931 | E9: 0.001039 | F9: 1.67165e-05 | N9: =(B9*$D$38)+($C$38*C9)+($H$38*D9)+($E$38*E9)+(F9*$F$38)+(G9*$G$38)+(H9*$I$38/2)+(I9*$I$38/2)+(J9*$J$38/2)+(K9*$J$38/2) -> 0.00037349549 | O9: =($B9*$D$39)+($C$39*$C9)+($H$39*$D9)+($E$39*$E9)+($F9*$F$39)+($G9*$G$39)+($H9*$I$39/2)+($I9*$I$39/2)+($J9*$J$39/2)+($K9*$J$39/2) -> 0.00048138148 | P9: =($B9*$D$40)+($C$40*$C9)+($H$40*$D9)+($E$40*$E9)+($F9*$F$40)+($G9*$G$40)+($H9*$I$40/2)+($I9*$I$40/2)+($J9*$J$40/2)+($K9*$J$40/2) -> 6.0504166e-05 | Q9: =($B9*$D$41)+($C$41*$C9)+($H$41*$D9)+($E$41*$E9)+($F9*$F$41)+($G9*$G$41)+($H9*$I$41/2)+($I9*$I$41/2)+($J9*$J$41/2)+($K9*$J$41/2) -> 0.00087645174
A10: Chlorine | G10: 0.13236565 | N10: =(B10*$D$38)+($C$38*C10)+($H$38*D10)+($E$38*E10)+(F10*$F$38)+(G10*$G$38)+(H10*$I$38/2)+(I10*$I$38/2)+(J10*$J$38/2)+(K10*$J$38/2) -> 0.00024056537 | O10: =($B10*$D$39)+($C$39*$C10)+($H$39*$D10)+($E$39*$E10)+($F10*$F$39)+($G10*$G$39)+($H10*$I$39/2)+($I10*$I$39/2)+($J10*$J$39/2)+($K10*$J$39/2) -> 8.3346827e-05 | P10: =($B10*$D$40)+($C$40*$C10)+($H$40*$D10)+($E$40*$E10)+($F10*$F$40)+($G10*$G$40)+($H10*$I$40/2)+($I10*$I$40/2)+($J10*$J$40/2)+($K10*$J$40/2) -> 1.8161642e-05 | Q10: =($B10*$D$41)+($C$41*$C10)+($H$41*$D10)+($E$41*$E10)+($F10*$F$41)+($G10*$G$41)+($H10*$I$41/2)+($I10*$I$41/2)+($J10*$J$41/2)+($K10*$J$41/2) -> 1.0922625e-05
A11: Cumene | B11: 0.015 | N11: =(B11*$D$38)+($C$38*C11)+($H$38*D11)+($E$38*E11)+(F11*$F$38)+(G11*$G$38)+(H11*$I$38/2)+(I11*$I$38/2)+(J11*$J$38/2)+(K11*$J$38/2) -> 0.0093806298 | O11: =($B11*$D$39)+($C$39*$C11)+($H$39*$D11)+($E$39*$E11)+($F11*$F$39)+($G11*$G$39)+($H11*$I$39/2)+($I11*$I$39/2)+($J11*$J$39/2)+($K11*$J$39/2) -> 0.0053543414 | P11: =($B11*$D$40)+($C$40*$C11)+($H$40*$D11)+($E$40*$E11)+($F11*$F$40)+($G11*$G$40)+($H11*$I$40/2)+($I11*$I$40/2)+($J11*$J$40/2)+($K11*$J$40/2) -> 0.0084584946 | Q11: =($B11*$D$41)+($C$41*$C11)+($H$41*$D11)+($E$41*$E11)+($F11*$F$41)+($G11*$G$41)+($H11*$I$41/2)+($I11*$I$41/2)+($J11*$J$41/2)+($K11*$J$41/2) -> 0.00329301
A12: Styrene | F12: 0.00017227 | N12: =(B12*$D$38)+($C$38*C12)+($H$38*D12)+($E$38*E12)+(F12*$F$38)+(G12*$G$38)+(H12*$I$38/2)+(I12*$I$38/2)+(J12*$J$38/2)+(K12*$J$38/2) -> 4.6783229e-07 | O12: =($B12*$D$39)+($C$39*$C12)+($H$39*$D12)+($E$39*$E12)+($F12*$F$39)+($G12*$G$39)+($H12*$I$39/2)+($I12*$I$39/2)+($J12*$J$39/2)+($K12*$J$39/2) -> 3.6607258e-07 | P12: =($B12*$D$40)+($C$40*$C12)+($H$40*$D12)+($E$40*$E12)+($F12*$F$40)+($G12*$G$40)+($H12*$I$40/2)+($I12*$I$40/2)+($J12*$J$40/2)+($K12*$J$40/2) -> 2.6970389e-07 | Q12: =($B12*$D$41)+($C$41*$C12)+($H$41*$D12)+($E$41*$E12)+($F12*$F$41)+($G12*$G$41)+($H12*$I$41/2)+($I12*$I$41/2)+($J12*$J$41/2)+($K12*$J$41/2) -> 1.2287929e-07
A13: Methanol | J13: 0.7446465 | N13: =(B13*$D$38)+($C$38*C13)+($H$38*D13)+($E$38*E13)+(F13*$F$38)+(G13*$G$38)+(H13*$I$38/2)+(I13*$I$38/2)+(J13*$J$38/2)+(K13*$J$38/2) -> 0.016283427 | O13: =($B13*$D$39)+($C$39*$C13)+($H$39*$D13)+($E$39*$E13)+($F13*$F$39)+($G13*$G$39)+($H13*$I$39/2)+($I13*$I$39/2)+($J13*$J$39/2)+($K13*$J$39/2) -> 0.010922765 | P13: =($B13*$D$40)+($C$40*$C13)+($H$40*$D13)+($E$40*$E13)+($F13*$F$40)+($G13*$G$40)+($H13*$I$40/2)+($I13*$I$40/2)+($J13*$J$40/2)+($K13*$J$40/2) -> 0.0023248388 | Q13: =($B13*$D$41)+($C$41*$C13)+($H$41*$D13)+($E$41*$E13)+($F13*$F$41)+($G13*$G$41)+($H13*$I$41/2)+($I13*$I$41/2)+($J13*$J$41/2)+($K13*$J$41/2) -> 0.0011438081
A14: Ethylene Glycol | K14: 0.000572 | N14: =(B14*$D$38)+($C$38*C14)+($H$38*D14)+($E$38*E14)+(F14*$F$38)+(G14*$G$38)+(H14*$I$38/2)+(I14*$I$38/2)+(J14*$J$38/2)+(K14*$J$38/2) -> 1.250811e-05 | O14: =($B14*$D$39)+($C$39*$C14)+($H$39*$D14)+($E$39*$E14)+($F14*$F$39)+($G14*$G$39)+($H14*$I$39/2)+($I14*$I$39/2)+($J14*$J$39/2)+($K14*$J$39/2) -> 8.390319e-06 | P14: =($B14*$D$40)+($C$40*$C14)+($H$40*$D14)+($E$40*$E14)+($F14*$F$40)+($G14*$G$40)+($H14*$I$40/2)+($I14*$I$40/2)+($J14*$J$40/2)+($K14*$J$40/2) -> 1.7858243e-06 | Q14: =($B14*$D$41)+($C$41*$C14)+($H$41*$D14)+($E$41*$E14)+($F14*$F$41)+($G14*$G$41)+($H14*$I$41/2)+($I14*$I$41/2)+($J14*$J$41/2)+($K14*$J$41/2) -> 8.7861591e-07
A15: Naphthalene | B15: 0 | C15: 0.0010744 | E15: 0.00081165 | F15: 0.000117885 | G15: 3.6125e-05 | N15: =(B15*$D$38)+($C$38*C15)+($H$38*D15)+($E$38*E15)+(F15*$F$38)+(G15*$G$38)+(H15*$I$38/2)+(I15*$I$38/2)+(J15*$J$38/2)+(K15*$J$38/2) -> 0.00020818347 | O15: =($B15*$D$39)+($C$39*$C15)+($H$39*$D15)+($E$39*$E15)+($F15*$F$39)+($G15*$G$39)+($H15*$I$39/2)+($I15*$I$39/2)+($J15*$J$39/2)+($K15*$J$39/2) -> 0.00026812348 | P15: =($B15*$D$40)+($C$40*$C15)+($H$40*$D15)+($E$40*$E15)+($F15*$F$40)+($G15*$G$40)+($H15*$I$40/2)+($I15*$I$40/2)+($J15*$J$40/2)+($K15*$J$40/2) -> 3.4013566e-05 | Q15: =($B15*$D$41)+($C$41*$C15)+($H$41*$D15)+($E$41*$E15)+($F15*$F$41)+($G15*$G$41)+($H15*$I$41/2)+($I15*$I$41/2)+($J15*$J$41/2)+($K15*$J$41/2) -> 0.00048775531
A16: Cyclohexane | C16: 1.4743936 | D16: 74.489555 | N16: =(B16*$D$38)+($C$38*C16)+($H$38*D16)+($E$38*E16)+(F16*$F$38)+(G16*$G$38)+(H16*$I$38/2)+(I16*$I$38/2)+(J16*$J$38/2)+(K16*$J$38/2) -> 8.8674841 | O16: =($B16*$D$39)+($C$39*$C16)+($H$39*$D16)+($E$39*$E16)+($F16*$F$39)+($G16*$G$39)+($H16*$I$39/2)+($I16*$I$39/2)+($J16*$J$39/2)+($K16*$J$39/2) -> 26.912548 | P16: =($B16*$D$40)+($C$40*$C16)+($H$40*$D16)+($E$40*$E16)+($F16*$F$40)+($G16*$G$40)+($H16*$I$40/2)+($I16*$I$40/2)+($J16*$J$40/2)+($K16*$J$40/2) -> 29.000786 | Q16: =($B16*$D$41)+($C$41*$C16)+($H$41*$D16)+($E$41*$E16)+($F16*$F$41)+($G16*$G$41)+($H16*$I$41/2)+($I16*$I$41/2)+($J16*$J$41/2)+($K16*$J$41/2) -> 24.535861
A17: Cyclopentane | D17: 49.894182 | N17: =(B17*$D$38)+($C$38*C17)+($H$38*D17)+($E$38*E17)+(F17*$F$38)+(G17*$G$38)+(H17*$I$38/2)+(I17*$I$38/2)+(J17*$J$38/2)+(K17*$J$38/2) -> 5.7486024 | O17: =($B17*$D$39)+($C$39*$C17)+($H$39*$D17)+($E$39*$E17)+($F17*$F$39)+($G17*$G$39)+($H17*$I$39/2)+($I17*$I$39/2)+($J17*$J$39/2)+($K17*$J$39/2) -> 17.780311 | P17: =($B17*$D$40)+($C$40*$C17)+($H$40*$D17)+($E$40*$E17)+($F17*$F$40)+($G17*$G$40)+($H17*$I$40/2)+($I17*$I$40/2)+($J17*$J$40/2)+($K17*$J$40/2) -> 19.394612 | Q17: =($B17*$D$41)+($C$41*$C17)+($H$41*$D17)+($E$41*$E17)+($F17*$F$41)+($G17*$G$41)+($H17*$I$41/2)+($I17*$I$41/2)+($J17*$J$41/2)+($K17*$J$41/2) -> 15.986286
A18: 1,2,4-Trimethylbenzene | C18: 0.0128163 | N18: =(B18*$D$38)+($C$38*C18)+($H$38*D18)+($E$38*E18)+(F18*$F$38)+(G18*$G$38)+(H18*$I$38/2)+(I18*$I$38/2)+(J18*$J$38/2)+(K18*$J$38/2) -> 0.0024782928 | O18: =($B18*$D$39)+($C$39*$C18)+($H$39*$D18)+($E$39*$E18)+($F18*$F$39)+($G18*$G$39)+($H18*$I$39/2)+($I18*$I$39/2)+($J18*$J$39/2)+($K18*$J$39/2) -> 0.003193828 | P18: =($B18*$D$40)+($C$40*$C18)+($H$40*$D18)+($E$40*$E18)+($F18*$F$40)+($G18*$G$40)+($H18*$I$40/2)+($I18*$I$40/2)+($J18*$J$40/2)+($K18*$J$40/2) -> 0.00039625227 | Q18: =($B18*$D$41)+($C$41*$C18)+($H$41*$D18)+($E$41*$E18)+($F18*$F$41)+($G18*$G$41)+($H18*$I$41/2)+($I18*$I$41/2)+($J18*$J$41/2)+($K18*$J$41/2) -> 0.0058164278
A19: PAC | C19: 0.0006801 | G19: 0.14148035 | N19: =(B19*$D$38)+($C$38*C19)+($H$38*D19)+($E$38*E19)+(F19*$F$38)+(G19*$G$38)+(H19*$I$38/2)+(I19*$I$38/2)+(J19*$J$38/2)+(K19*$J$38/2) -> 0.0003886419 | O19: =($B19*$D$39)+($C$39*$C19)+($H$39*$D19)+($E$39*$E19)+($F19*$F$39)+($G19*$G$39)+($H19*$I$39/2)+($I19*$I$39/2)+($J19*$J$39/2)+($K19*$J$39/2) -> 0.00025856733 | P19: =($B19*$D$40)+($C$40*$C19)+($H$40*$D19)+($E$40*$E19)+($F19*$F$40)+($G19*$G$40)+($H19*$I$40/2)+($I19*$I$40/2)+($J19*$J$40/2)+($K19*$J$40/2) -> 4.0439474e-05 | Q19: =($B19*$D$41)+($C$41*$C19)+($H$41*$D19)+($E$41*$E19)+($F19*$F$41)+($G19*$G$41)+($H19*$I$41/2)+($I19*$I$41/2)+($J19*$J$41/2)+($K19*$J$41/2) -> 0.00032032488
A20: Ethanol | B20: 10.155 | N20: =(B20*$D$38)+($C$38*C20)+($H$38*D20)+($E$38*E20)+(F20*$F$38)+(G20*$G$38)+(H20*$I$38/2)+(I20*$I$38/2)+(J20*$J$38/2)+(K20*$J$38/2) -> 6.3506864 | O20: =($B20*$D$39)+($C$39*$C20)+($H$39*$D20)+($E$39*$E20)+($F20*$F$39)+($G20*$G$39)+($H20*$I$39/2)+($I20*$I$39/2)+($J20*$J$39/2)+($K20*$J$39/2) -> 3.6248891 | P20: =($B20*$D$40)+($C$40*$C20)+($H$40*$D20)+($E$40*$E20)+($F20*$F$40)+($G20*$G$40)+($H20*$I$40/2)+($I20*$I$40/2)+($J20*$J$40/2)+($K20*$J$40/2) -> 5.7264008 | Q20: =($B20*$D$41)+($C$41*$C20)+($H$41*$D20)+($E$41*$E20)+($F20*$F$41)+($G20*$G$41)+($H20*$I$41/2)+($I20*$I$41/2)+($J20*$J$41/2)+($K20*$J$41/2) -> 2.2293678
A21: n-Butane | B21: 200.04 | C21: 105.62115 | D21: 298.82772 | N21: =(B21*$D$38)+($C$38*C21)+($H$38*D21)+($E$38*E21)+(F21*$F$38)+(G21*$G$38)+(H21*$I$38/2)+(I21*$I$38/2)+(J21*$J$38/2)+(K21*$J$38/2) -> 179.95378 | O21: =($B21*$D$39)+($C$39*$C21)+($H$39*$D21)+($E$39*$E21)+($F21*$F$39)+($G21*$G$39)+($H21*$I$39/2)+($I21*$I$39/2)+($J21*$J$39/2)+($K21*$J$39/2) -> 204.21671 | P21: =($B21*$D$40)+($C$40*$C21)+($H$40*$D21)+($E$40*$E21)+($F21*$F$40)+($G21*$G$40)+($H21*$I$40/2)+($I21*$I$40/2)+($J21*$J$40/2)+($K21*$J$40/2) -> 232.22685 | Q21: =($B21*$D$41)+($C$41*$C21)+($H$41*$D21)+($E$41*$E21)+($F21*$F$41)+($G21*$G$41)+($H21*$I$41/2)+($I21*$I$41/2)+($J21*$J$41/2)+($K21*$J$41/2) -> 187.59522
A22: Isobutane | B22: 26.71 | N22: =(B22*$D$38)+($C$38*C22)+($H$38*D22)+($E$38*E22)+(F22*$F$38)+(G22*$G$38)+(H22*$I$38/2)+(I22*$I$38/2)+(J22*$J$38/2)+(K22*$J$38/2) -> 16.703775 | O22: =($B22*$D$39)+($C$39*$C22)+($H$39*$D22)+($E$39*$E22)+($F22*$F$39)+($G22*$G$39)+($H22*$I$39/2)+($I22*$I$39/2)+($J22*$J$39/2)+($K22*$J$39/2) -> 9.5342973 | P22: =($B22*$D$40)+($C$40*$C22)+($H$40*$D22)+($E$40*$E22)+($F22*$F$40)+($G22*$G$40)+($H22*$I$40/2)+($I22*$I$40/2)+($J22*$J$40/2)+($K22*$J$40/2) -> 15.061759 | Q22: =($B22*$D$41)+($C$41*$C22)+($H$41*$D22)+($E$41*$E22)+($F22*$F$41)+($G22*$G$41)+($H22*$I$41/2)+($I22*$I$41/2)+($J22*$J$41/2)+($K22*$J$41/2) -> 5.8637531
A23: Pentane | B23: 47.045 | C23: 70.648886 | D23: 824.37516 | N23: =(B23*$D$38)+($C$38*C23)+($H$38*D23)+($E$38*E23)+(F23*$F$38)+(G23*$G$38)+(H23*$I$38/2)+(I23*$I$38/2)+(J23*$J$38/2)+(K23*$J$38/2) -> 138.0633 | O23: =($B23*$D$39)+($C$39*$C23)+($H$39*$D23)+($E$39*$E23)+($F23*$F$39)+($G23*$G$39)+($H23*$I$39/2)+($I23*$I$39/2)+($J23*$J$39/2)+($K23*$J$39/2) -> 328.17341 | P23: =($B23*$D$40)+($C$40*$C23)+($H$40*$D23)+($E$40*$E23)+($F23*$F$40)+($G23*$G$40)+($H23*$I$40/2)+($I23*$I$40/2)+($J23*$J$40/2)+($K23*$J$40/2) -> 349.15988 | Q23: =($B23*$D$41)+($C$41*$C23)+($H$41*$D23)+($E$41*$E23)+($F23*$F$41)+($G23*$G$41)+($H23*$I$41/2)+($I23*$I$41/2)+($J23*$J$41/2)+($K23*$J$41/2) -> 306.52353
A24: Isopentane | B24: 33.165 | N24: =(B24*$D$38)+($C$38*C24)+($H$38*D24)+($E$38*E24)+(F24*$F$38)+(G24*$G$38)+(H24*$I$38/2)+(I24*$I$38/2)+(J24*$J$38/2)+(K24*$J$38/2) -> 20.740573 | O24: =($B24*$D$39)+($C$39*$C24)+($H$39*$D24)+($E$39*$E24)+($F24*$F$39)+($G24*$G$39)+($H24*$I$39/2)+($I24*$I$39/2)+($J24*$J$39/2)+($K24*$J$39/2) -> 11.838449 | P24: =($B24*$D$40)+($C$40*$C24)+($H$40*$D24)+($E$40*$E24)+($F24*$F$40)+($G24*$G$40)+($H24*$I$40/2)+($I24*$I$40/2)+($J24*$J$40/2)+($K24*$J$40/2) -> 18.701732 | Q24: =($B24*$D$41)+($C$41*$C24)+($H$41*$D24)+($E$41*$E24)+($F24*$F$41)+($G24*$G$41)+($H24*$I$41/2)+($I24*$I$41/2)+($J24*$J$41/2)+($K24*$J$41/2) -> 7.2808451
A25: C6 | B25: 47.305 | C25: 14.441899 | D25: =327.31628+142.789 -> 470.10528 | F25: 0.75317115 | G25: 0.17152175 | N25: =(B25*$D$38)+($C$38*C25)+($H$38*D25)+($E$38*E25)+(F25*$F$38)+(G25*$G$38)+(H25*$I$38/2)+(I25*$I$38/2)+(J25*$J$38/2)+(K25*$J$38/2) -> 86.541969 | O25: =($B25*$D$39)+($C$39*$C25)+($H$39*$D25)+($E$39*$E25)+($F25*$F$39)+($G25*$G$39)+($H25*$I$39/2)+($I25*$I$39/2)+($J25*$J$39/2)+($K25*$J$39/2) -> 188.01336 | P25: =($B25*$D$40)+($C$40*$C25)+($H$40*$D25)+($E$40*$E25)+($F25*$F$40)+($G25*$G$40)+($H25*$I$40/2)+($I25*$I$40/2)+($J25*$J$40/2)+($K25*$J$40/2) -> 209.85992 | Q25: =($B25*$D$41)+($C$41*$C25)+($H$41*$D25)+($E$41*$E25)+($F25*$F$41)+($G25*$G$41)+($H25*$I$41/2)+($I25*$I$41/2)+($J25*$J$41/2)+($K25*$J$41/2) -> 167.5633
A26: C7 | B26: =10.2+24.89 -> 35.09 | C26: 77.720771 | D26: 19.962374 | E26: 0.017373 | F26: 0.3067536 | G26: 0.0516948 | N26: =(B26*$D$38)+($C$38*C26)+($H$38*D26)+($E$38*E26)+(F26*$F$38)+(G26*$G$38)+(H26*$I$38/2)+(I26*$I$38/2)+(J26*$J$38/2)+(K26*$J$38/2) -> 39.274226 | O26: =($B26*$D$39)+($C$39*$C26)+($H$39*$D26)+($E$39*$E26)+($F26*$F$39)+($G26*$G$39)+($H26*$I$39/2)+($I26*$I$39/2)+($J26*$J$39/2)+($K26*$J$39/2) -> 39.008129 | P26: =($B26*$D$40)+($C$40*$C26)+($H$40*$D26)+($E$40*$E26)+($F26*$F$40)+($G26*$G$40)+($H26*$I$40/2)+($I26*$I$40/2)+($J26*$J$40/2)+($K26*$J$40/2) -> 29.950369 | Q26: =($B26*$D$41)+($C$41*$C26)+($H$41*$D26)+($E$41*$E26)+($F26*$F$41)+($G26*$G$41)+($H26*$I$41/2)+($I26*$I$41/2)+($J26*$J$41/2)+($K26*$J$41/2) -> 49.371749
A27: 2,3,4-Trimethylpentane (surrogate for C8 cpds) | B27: 1.825 | D27: 44.698106 | E27: 0.7768456 | G27: 0.0431058 | N27: =(B27*$D$38)+($C$38*C27)+($H$38*D27)+($E$38*E27)+(F27*$F$38)+(G27*$G$38)+(H27*$I$38/2)+(I27*$I$38/2)+(J27*$J$38/2)+(K27*$J$38/2) -> 6.291359 | O27: =($B27*$D$39)+($C$39*$C27)+($H$39*$D27)+($E$39*$E27)+($F27*$F$39)+($G27*$G$39)+($H27*$I$39/2)+($I27*$I$39/2)+($J27*$J$39/2)+($K27*$J$39/2) -> 16.580212 | P27: =($B27*$D$40)+($C$40*$C27)+($H$40*$D27)+($E$40*$E27)+($F27*$F$40)+($G27*$G$40)+($H27*$I$40/2)+($I27*$I$40/2)+($J27*$J$40/2)+($K27*$J$40/2) -> 18.404523 | Q27: =($B27*$D$41)+($C$41*$C27)+($H$41*$D27)+($E$41*$E27)+($F27*$F$41)+($G27*$G$41)+($H27*$I$41/2)+($I27*$I$41/2)+($J27*$J$41/2)+($K27*$J$41/2) -> 14.722166
A28: 1,2,4-Trimethylbenzene (surrogate for C9 cpds) | B28: 0.29 | D28: 1.3347351 | E28: 0.3735681 | F28: 0.0017178 | G28: 0.00300345 | N28: =(B28*$D$38)+($C$38*C28)+($H$38*D28)+($E$38*E28)+(F28*$F$38)+(G28*$G$38)+(H28*$I$38/2)+(I28*$I$38/2)+(J28*$J$38/2)+(K28*$J$38/2) -> 0.33517032 | O28: =($B28*$D$39)+($C$39*$C28)+($H$39*$D28)+($E$39*$E28)+($F28*$F$39)+($G28*$G$39)+($H28*$I$39/2)+($I28*$I$39/2)+($J28*$J$39/2)+($K28*$J$39/2) -> 0.57921986 | P28: =($B28*$D$40)+($C$40*$C28)+($H$40*$D28)+($E$40*$E28)+($F28*$F$40)+($G28*$G$40)+($H28*$I$40/2)+($I28*$I$40/2)+($J28*$J$40/2)+($K28*$J$40/2) -> 0.68264433 | Q28: =($B28*$D$41)+($C$41*$C28)+($H$41*$D28)+($E$41*$E28)+($F28*$F$41)+($G28*$G$41)+($H28*$I$41/2)+($I28*$I$41/2)+($J28*$J$41/2)+($K28*$J$41/2) -> 0.49135404
A29: Decane | D29: 1.0631623 | E29: 0.36001115 | F29: 0.12452405 | G29: 0.2268812 | N29: =(B29*$D$38)+($C$38*C29)+($H$38*D29)+($E$38*E29)+(F29*$F$38)+(G29*$G$38)+(H29*$I$38/2)+(I29*$I$38/2)+(J29*$J$38/2)+(K29*$J$38/2) -> 0.12326167 | O29: =($B29*$D$39)+($C$39*$C29)+($H$39*$D29)+($E$39*$E29)+($F29*$F$39)+($G29*$G$39)+($H29*$I$39/2)+($I29*$I$39/2)+($J29*$J$39/2)+($K29*$J$39/2) -> 0.37932489 | P29: =($B29*$D$40)+($C$40*$C29)+($H$40*$D29)+($E$40*$E29)+($F29*$F$40)+($G29*$G$40)+($H29*$I$40/2)+($I29*$I$40/2)+($J29*$J$40/2)+($K29*$J$40/2) -> 0.41376188 | Q29: =($B29*$D$41)+($C$41*$C29)+($H$41*$D29)+($E$41*$E29)+($F29*$F$41)+($G29*$G$41)+($H29*$I$41/2)+($I29*$I$41/2)+($J29*$J$41/2)+($K29*$J$41/2) -> 0.34078106
N33: =N22+N21 -> 196.65756
N34: =N4+N25 -> 105.41608
C37: Crude Petroleum | D37: Gasoline | E37: Kerosene | F37: Distillate Fuel Oil | G37: Residual Fuel Oil | H37: Naphtha & Solvents | I37: Benzene & Toluene | J37: Alcohols | K37: Total
A38: Percent Loading | B38: 50000 | C38: 0.19337038 | D38: 0.62537532 | E38: 4.9938416e-05 | F38: 0.0027156922 | G38: 0.0018174305 | H38: 0.11521589 | I38: 0.0177207 | J38: 0.043734649 | K38: 1
A39: Percent Loading | B39: 500000 | C39: 0.24920047 | D39: 0.3569561 | E39: 0.00013459718 | F39: 0.0021249932 | G39: 0.00062967112 | H39: 0.35636041 | I39: 0.005256979 | J39: 0.02933678 | K39: 1
A40: Percent Loading | B40: 5000000 | C40: 0.030917836 | D40: 0.56389964 | E40: 0.00074653737 | F40: 0.0015655883 | G40: 0.00013720812 | H40: 0.38871491 | I40: 0.0077741398 | J40: 0.0062441409 | K40: 1
A41: Percent Loading | B41: 25000000 | C41: 0.4538305 | D41: 0.219534 | E41: 8.9638012e-05 | F41: 0.00071329476 | G41: 8.2518573e-05 | H41: 0.3204038 | I41: 0.0022741681 | J41: 0.0030720836 | K41: 1
